Blocking_Assignments/bad_shift_reg2.v
module bad_shift_reg2 (
	input 		clk , 
	input 		reset , 
	input 		d , 
	output 	reg 	dout
);

reg q1;
always @ (posedge clk , posedge reset)
begin
	if(reset)
	begin
		q1 = 1'b0;
		dout = 1'b0;
	end
	else
	begin
		// 2 FFs are inferred but having blocking assignments is bad idea
		// if order is assignments is swapped then it causes problem
		dout = q1;
		q1 = d;
	end
end

endmodule

Blocking_Assignments/tb_bad_shift_reg2.v
`timescale 1ns / 1ps
module tb_bad_shift_reg2;
	// Inputs
	reg clk, reset,  d;
	// Outputs
	wire dout;

        // Instantiate the Unit Under Test (UUT)
	bad_shift_reg2 uut (
		.clk(clk),
		.reset(reset),
		.d(d),
		.dout(dout)
	);

	initial begin
	$dumpfile("tb_bad_shift_reg2.vcd");
	$dumpvars(0,tb_bad_shift_reg2);
	// Initialize Inputs
	clk = 0;
	reset = 1;
	d = 0;
	#3000 $finish;
	end

	always #20 clk = ~clk;
	always #223 d = ~d;
	always #113 reset = 0;

endmodule

Blocking_Assignments/tb_bad_shift_reg2.vcd
$date
	Wed Jun  2 22:38:18 2021
$end
$version
	Icarus Verilog
$end
$timescale
	1ps
$end
$scope module tb_bad_shift_reg2 $end
$var wire 1 ! dout $end
$var reg 1 " clk $end
$var reg 1 # d $end
$var reg 1 $ reset $end
$scope module uut $end
$var wire 1 " clk $end
$var wire 1 # d $end
$var wire 1 $ reset $end
$var reg 1 ! dout $end
$var reg 1 % q1 $end
$upscope $end
$upscope $end
$enddefinitions $end
#0
$dumpvars
0%
1$
0#
0"
0!
$end
#20000
1"
#40000
0"
#60000
1"
#80000
0"
#100000
1"
#113000
0$
#120000
0"
#140000
1"
#160000
0"
#180000
1"
#200000
0"
#220000
1"
#223000
1#
#240000
0"
#260000
1%
1"
#280000
0"
#300000
1!
1"
#320000
0"
#340000
1"
#360000
0"
#380000
1"
#400000
0"
#420000
1"
#440000
0"
#446000
0#
#460000
0%
1"
#480000
0"
#500000
0!
1"
#520000
0"
#540000
1"
#560000
0"
#580000
1"
#600000
0"
#620000
1"
#640000
0"
#660000
1"
#669000
1#
#680000
0"
#700000
1%
1"
#720000
0"
#740000
1!
1"
#760000
0"
#780000
1"
#800000
0"
#820000
1"
#840000
0"
#860000
1"
#880000
0"
#892000
0#
#900000
0%
1"
#920000
0"
#940000
0!
1"
#960000
0"
#980000
1"
#1000000
0"
#1020000
1"
#1040000
0"
#1060000
1"
#1080000
0"
#1100000
1"
#1115000
1#
#1120000
0"
#1140000
1%
1"
#1160000
0"
#1180000
1!
1"
#1200000
0"
#1220000
1"
#1240000
0"
#1260000
1"
#1280000
0"
#1300000
1"
#1320000
0"
#1338000
0#
#1340000
0%
1"
#1360000
0"
#1380000
0!
1"
#1400000
0"
#1420000
1"
#1440000
0"
#1460000
1"
#1480000
0"
#1500000
1"
#1520000
0"
#1540000
1"
#1560000
0"
#1561000
1#
#1580000
1%
1"
#1600000
0"
#1620000
1!
1"
#1640000
0"
#1660000
1"
#1680000
0"
#1700000
1"
#1720000
0"
#1740000
1"
#1760000
0"
#1780000
1"
#1784000
0#
#1800000
0"
#1820000
0%
1"
#1840000
0"
#1860000
0!
1"
#1880000
0"
#1900000
1"
#1920000
0"
#1940000
1"
#1960000
0"
#1980000
1"
#2000000
0"
#2007000
1#
#2020000
1%
1"
#2040000
0"
#2060000
1!
1"
#2080000
0"
#2100000
1"
#2120000
0"
#2140000
1"
#2160000
0"
#2180000
1"
#2200000
0"
#2220000
1"
#2230000
0#
#2240000
0"
#2260000
0%
1"
#2280000
0"
#2300000
0!
1"
#2320000
0"
#2340000
1"
#2360000
0"
#2380000
1"
#2400000
0"
#2420000
1"
#2440000
0"
#2453000
1#
#2460000
1%
1"
#2480000
0"
#2500000
1!
1"
#2520000
0"
#2540000
1"
#2560000
0"
#2580000
1"
#2600000
0"
#2620000
1"
#2640000
0"
#2660000
1"
#2676000
0#
#2680000
0"
#2700000
0%
1"
#2720000
0"
#2740000
0!
1"
#2760000
0"
#2780000
1"
#2800000
0"
#2820000
1"
#2840000
0"
#2860000
1"
#2880000
0"
#2899000
1#
#2900000
1%
1"
#2920000
0"
#2940000
1!
1"
