Blocking_Assignments/blocking_caveat.v
module blocking_caveat (
	input 		a , 
	input 		b , 
	input  		c, 
	output 	reg 	d
); 

reg x;
always @ (*)
begin
	// previous value of x is considered
	// as the order of assignments is swapped
	d = x & c;
	x = a | b;
end

endmodule

Blocking_Assignments/tb_blocking_caveat.v
`timescale 1ns / 1ps
module tb_blocking_caveat;
	// Inputs
	reg a,b,c   ;
	// Output
	wire d;

        // Instantiate the Unit Under Test (UUT)
	blocking_caveat uut (
		.a(a),
		.b(b),
		.c(c),
		.d(d)
	);

	initial begin
	$dumpfile("tb_blocking_caveat.vcd");
	$dumpvars(0,tb_blocking_caveat);
	// Initialize Inputs
	a = 0;
	b = 0;
	c = 0;
	#3000 $finish;
	end

	always #10 a = ~a;
	always #100 c =~c;
	always #50 b = ~b;

endmodule

Blocking_Assignments/tb_blocking_caveat.vcd
$date
	Wed Jun  2 21:00:47 2021
$end
$version
	Icarus Verilog
$end
$timescale
	1ps
$end
$scope module tb_blocking_caveat $end
$var wire 1 ! d $end
$var reg 1 " a $end
$var reg 1 # b $end
$var reg 1 $ c $end
$scope module uut $end
$var wire 1 " a $end
$var wire 1 # b $end
$var wire 1 $ c $end
$var reg 1 ! d $end
$var reg 1 % x $end
$upscope $end
$upscope $end
$enddefinitions $end
#0
$dumpvars
0%
0$
0#
0"
0!
$end
#10000
1%
1"
#20000
0%
0"
#30000
1%
1"
#40000
0%
0"
#50000
1%
1"
1#
#60000
0"
#70000
1"
#80000
0"
#90000
1"
#100000
0%
1!
0"
0#
1$
#110000
1%
0!
1"
#120000
0%
1!
0"
#130000
1%
0!
1"
#140000
0%
1!
0"
#150000
1%
0!
1"
1#
#160000
1!
0"
#170000
1"
#180000
0"
#190000
1"
#200000
0%
0!
0"
0#
0$
#210000
1%
1"
#220000
0%
0"
#230000
1%
1"
#240000
0%
0"
#250000
1%
1"
1#
#260000
0"
#270000
1"
#280000
0"
#290000
1"
#300000
0%
1!
0"
0#
1$
#310000
1%
0!
1"
#320000
0%
1!
0"
#330000
1%
0!
1"
#340000
0%
1!
0"
#350000
1%
0!
1"
1#
#360000
1!
0"
#370000
1"
#380000
0"
#390000
1"
#400000
0%
0!
0"
0#
0$
#410000
1%
1"
#420000
0%
0"
#430000
1%
1"
#440000
0%
0"
#450000
1%
1"
1#
#460000
0"
#470000
1"
#480000
0"
#490000
1"
#500000
0%
1!
0"
0#
1$
#510000
1%
0!
1"
#520000
0%
1!
0"
#530000
1%
0!
1"
#540000
0%
1!
0"
#550000
1%
0!
1"
1#
#560000
1!
0"
#570000
1"
#580000
0"
#590000
1"
#600000
0%
0!
0"
0#
0$
#610000
1%
1"
#620000
0%
0"
#630000
1%
1"
#640000
0%
0"
#650000
1%
1"
1#
#660000
0"
#670000
1"
#680000
0"
#690000
1"
#700000
0%
1!
0"
0#
1$
#710000
1%
0!
1"
#720000
0%
1!
0"
#730000
1%
0!
1"
#740000
0%
1!
0"
#750000
1%
0!
1"
1#
#760000
1!
0"
#770000
1"
#780000
0"
#790000
1"
#800000
0%
0!
0"
0#
0$
#810000
1%
1"
#820000
0%
0"
#830000
1%
1"
#840000
0%
0"
#850000
1%
1"
1#
#860000
0"
#870000
1"
#880000
0"
#890000
1"
#900000
0%
1!
0"
0#
1$
#910000
1%
0!
1"
#920000
0%
1!
0"
#930000
1%
0!
1"
#940000
0%
1!
0"
#950000
1%
0!
1"
1#
#960000
1!
0"
#970000
1"
#980000
0"
#990000
1"
#1000000
0%
0!
0"
0#
0$
#1010000
1%
1"
#1020000
0%
0"
#1030000
1%
1"
#1040000
0%
0"
#1050000
1%
1"
1#
#1060000
0"
#1070000
1"
#1080000
0"
#1090000
1"
#1100000
0%
1!
0"
0#
1$
#1110000
1%
0!
1"
#1120000
0%
1!
0"
#1130000
1%
0!
1"
#1140000
0%
1!
0"
#1150000
1%
0!
1"
1#
#1160000
1!
0"
#1170000
1"
#1180000
0"
#1190000
1"
#1200000
0%
0!
0"
0#
0$
#1210000
1%
1"
#1220000
0%
0"
#1230000
1%
1"
#1240000
0%
0"
#1250000
1%
1"
1#
#1260000
0"
#1270000
1"
#1280000
0"
#1290000
1"
#1300000
0%
1!
0"
0#
1$
#1310000
1%
0!
1"
#1320000
0%
1!
0"
#1330000
1%
0!
1"
#1340000
0%
1!
0"
#1350000
1%
0!
1"
1#
#1360000
1!
0"
#1370000
1"
#1380000
0"
#1390000
1"
#1400000
0%
0!
0"
0#
0$
#1410000
1%
1"
#1420000
0%
0"
#1430000
1%
1"
#1440000
0%
0"
#1450000
1%
1"
1#
#1460000
0"
#1470000
1"
#1480000
0"
#1490000
1"
#1500000
0%
1!
0"
0#
1$
#1510000
1%
0!
1"
#1520000
0%
1!
0"
#1530000
1%
0!
1"
#1540000
0%
1!
0"
#1550000
1%
0!
1"
1#
#1560000
1!
0"
#1570000
1"
#1580000
0"
#1590000
1"
#1600000
0%
0!
0"
0#
0$
#1610000
1%
1"
#1620000
0%
0"
#1630000
1%
1"
#1640000
0%
0"
#1650000
1%
1"
1#
#1660000
0"
#1670000
1"
#1680000
0"
#1690000
1"
#1700000
0%
1!
0"
0#
1$
#1710000
1%
0!
1"
#1720000
0%
1!
0"
#1730000
1%
0!
1"
#1740000
0%
1!
0"
#1750000
1%
0!
1"
1#
#1760000
1!
0"
#1770000
1"
#1780000
0"
#1790000
1"
#1800000
0%
0!
0"
0#
0$
#1810000
1%
1"
#1820000
0%
0"
#1830000
1%
1"
#1840000
0%
0"
#1850000
1%
1"
1#
#1860000
0"
#1870000
1"
#1880000
0"
#1890000
1"
#1900000
0%
1!
0"
0#
1$
#1910000
1%
0!
1"
#1920000
0%
1!
0"
#1930000
1%
0!
1"
#1940000
0%
1!
0"
#1950000
1%
0!
1"
1#
#1960000
1!
0"
#1970000
1"
#1980000
0"
#1990000
1"
#2000000
0%
0!
0"
0#
0$
#2010000
1%
1"
#2020000
0%
0"
#2030000
1%
1"
#2040000
0%
0"
#2050000
1%
1"
1#
#2060000
0"
#2070000
1"
#2080000
0"
#2090000
1"
#2100000
0%
1!
0"
0#
1$
#2110000
1%
0!
1"
#2120000
0%
1!
0"
#2130000
1%
0!
1"
#2140000
0%
1!
0"
#2150000
1%
0!
1"
1#
#2160000
1!
0"
#2170000
1"
#2180000
0"
#2190000
1"
#2200000
0%
0!
0"
0#
0$
#2210000
1%
1"
#2220000
0%
0"
#2230000
1%
1"
#2240000
0%
0"
#2250000
1%
1"
1#
#2260000
0"
#2270000
1"
#2280000
0"
#2290000
1"
#2300000
0%
1!
0"
0#
1$
#2310000
1%
0!
1"
#2320000
0%
1!
0"
#2330000
1%
0!
1"
#2340000
0%
1!
0"
#2350000
1%
0!
1"
1#
#2360000
1!
0"
#2370000
1"
#2380000
0"
#2390000
1"
#2400000
0%
0!
0"
0#
0$
#2410000
1%
1"
#2420000
0%
0"
#2430000
1%
1"
#2440000
0%
0"
#2450000
1%
1"
1#
#2460000
0"
#2470000
1"
#2480000
0"
#2490000
1"
#2500000
0%
1!
0"
0#
1$
#2510000
1%
0!
1"
#2520000
0%
1!
0"
#2530000
1%
0!
1"
#2540000
0%
1!
0"
#2550000
1%
0!
1"
1#
#2560000
1!
0"
#2570000
1"
#2580000
0"
#2590000
1"
#2600000
0%
0!
0"
0#
0$
#2610000
1%
1"
#2620000
0%
0"
#2630000
1%
1"
#2640000
0%
0"
#2650000
1%
1"
1#
#2660000
0"
#2670000
1"
#2680000
0"
#2690000
1"
#2700000
0%
1!
0"
0#
1$
#2710000
1%
0!
1"
#2720000
0%
1!
0"
#2730000
1%
0!
1"
#2740000
0%
1!
0"
#2750000
1%
0!
1"
1#
#2760000
1!
0"
#2770000
1"
#2780000
0"
#2790000
1"
#2800000
0%
0!
0"
0#
0$
#2810000
1%
1"
#2820000
0%
0"
#2830000
1%
1"
#2840000
0%
0"
#2850000
1%
1"
1#
#2860000
0"
#2870000
1"
#2880000
0"
#2890000
1"
#2900000
0%
1!
0"
0#
1$
#2910000
1%
0!
1"
#2920000
0%
1!
0"
#2930000
1%
0!
1"
#2940000
0%
1!
0"
#2950000
1%
0!
1"
1#
#2960000
1!
0"
#2970000
1"
#2980000
0"
#2990000
1"
#3000000
0%
0!
0"
0#
0$
