if_Statement_and_Inferred_Latches/incomp_if1_net.v
/* Generated by Yosys 0.7 (git sha1 61f6811, gcc 6.2.0-11ubuntu1 -O2 -fdebug-prefix-map=/build/yosys-OIL3SR/yosys-0.7=. -fstack-protector-strong -fPIC -Os) */

module incomp_if1(i0, i1, i2, y);
  input i0;
  input i1;
  input i2;
  output y;
  \$_DLATCH_P_  _0_ (
    .D(i1),
    .E(i0),
    .Q(y)
  );
endmodule

if_Statement_and_Inferred_Latches/tb_incomp_if1.v
`timescale 1ns / 1ps
module tb_incomp_if1;
	//input
	reg i0,i1,i2;
	// Output
	wire y;

        // Instantiate the Unit Under Test (UUT)
	incomp_if1 uut (
		.i0(i0),
		.i1(i1),
		.i2(i2),
		.y(y)
	);

	initial begin
	$dumpfile("tb_incomp_if1.vcd");
	$dumpvars(0,tb_incomp_if1);
	// Initialize Inputs
	i0 = 1'b0;
	i1 = 1'b0;
	i2 = 1'b0;
	
	#3000 $finish;
	end

	always #317 i0 = ~i0;
	always #37 i1 = ~i1;
	always #57 i2 = ~i2;

endmodule

if_Statement_and_Inferred_Latches/tb_incomp_if1.vcd
$date
	Thu Jun  3 10:02:46 2021
$end
$version
	Icarus Verilog
$end
$timescale
	1ps
$end
$scope module tb_incomp_if1 $end
$var wire 1 ! y $end
$var reg 1 " i0 $end
$var reg 1 # i1 $end
$var reg 1 $ i2 $end
$scope module uut $end
$var wire 1 " i0 $end
$var wire 1 # i1 $end
$var wire 1 $ i2 $end
$var reg 1 ! y $end
$upscope $end
$upscope $end
$enddefinitions $end
#0
$dumpvars
0$
0#
0"
x!
$end
#37000
1#
#57000
1$
#74000
0#
#111000
1#
#114000
0$
#148000
0#
#171000
1$
#185000
1#
#222000
0#
#228000
0$
#259000
1#
#285000
1$
#296000
0#
#317000
0!
1"
#333000
1!
1#
#342000
0$
#370000
0!
0#
#399000
1$
#407000
1!
1#
#444000
0!
0#
#456000
0$
#481000
1!
1#
#513000
1$
#518000
0!
0#
#555000
1!
1#
#570000
0$
#592000
0!
0#
#627000
1$
#629000
1!
1#
#634000
0"
#666000
0#
#684000
0$
#703000
1#
#740000
0#
#741000
1$
#777000
1#
#798000
0$
#814000
0#
#851000
1#
#855000
1$
#888000
0#
#912000
0$
#925000
1#
#951000
1"
#962000
0!
0#
#969000
1$
#999000
1!
1#
#1026000
0$
#1036000
0!
0#
#1073000
1!
1#
#1083000
1$
#1110000
0!
0#
#1140000
0$
#1147000
1!
1#
#1184000
0!
0#
#1197000
1$
#1221000
1!
1#
#1254000
0$
#1258000
0!
0#
#1268000
0"
#1295000
1#
#1311000
1$
#1332000
0#
#1368000
0$
#1369000
1#
#1406000
0#
#1425000
1$
#1443000
1#
#1480000
0#
#1482000
0$
#1517000
1#
#1539000
1$
#1554000
0#
#1585000
1"
#1591000
1!
1#
#1596000
0$
#1628000
0!
0#
#1653000
1$
#1665000
1!
1#
#1702000
0!
0#
#1710000
0$
#1739000
1!
1#
#1767000
1$
#1776000
0!
0#
#1813000
1!
1#
#1824000
0$
#1850000
0!
0#
#1881000
1$
#1887000
1!
1#
#1902000
0"
#1924000
0#
#1938000
0$
#1961000
1#
#1995000
1$
#1998000
0#
#2035000
1#
#2052000
0$
#2072000
0#
#2109000
1#
1$
#2146000
0#
#2166000
0$
#2183000
1#
#2219000
1"
#2220000
0!
0#
#2223000
1$
#2257000
1!
1#
#2280000
0$
#2294000
0!
0#
#2331000
1!
1#
#2337000
1$
#2368000
0!
0#
#2394000
0$
#2405000
1!
1#
#2442000
0!
0#
#2451000
1$
#2479000
1!
1#
#2508000
0$
#2516000
0!
0#
#2536000
0"
#2553000
1#
#2565000
1$
#2590000
0#
#2622000
0$
#2627000
1#
#2664000
0#
#2679000
1$
#2701000
1#
#2736000
0$
#2738000
0#
#2775000
1#
#2793000
1$
#2812000
0#
#2849000
1#
#2850000
0$
#2853000
1!
1"
#2886000
0!
0#
#2907000
1$
#2923000
1!
1#
#2960000
0!
0#
#2964000
0$
#2997000
1!
1#
