if_Statement_and_Inferred_Latches/incomp_if2.v
module incomp_if2 (
	input 		i0 , 
	input 		i1 , 
	input 		i2 , 
	input 		i3 , 
	output 	reg 	y
);

always @ (*)
begin
	if(i0)
		y <= i1;
	else if (i2)
		y <= i3;

end

endmodule

if_Statement_and_Inferred_Latches/tb_incomp_if2.v
`timescale 1ns / 1ps
module tb_incomp_if2;
	//input
	reg i0,i1,i2,i3;
	// Output
	wire y;

        // Instantiate the Unit Under Test (UUT)
	incomp_if2 uut (
		.i0(i0),
		.i1(i1),
		.i2(i2),
		.i3(i3),
		.y(y)
	);

	initial begin
	$dumpfile("tb_incomp_if2.vcd");
	$dumpvars(0,tb_incomp_if2);
	// Initialize Inputs
	i0 = 1'b0;
	i1 = 1'b0;
	i2 = 1'b0;
	i3 = 1'b0;
	
	#3000 $finish;
	end

	always #317 i0 = ~i0;
	always #37 i1 = ~i1;
	always #157 i2 = ~i2;
	always #67 i3 = ~i3;

endmodule

if_Statement_and_Inferred_Latches/tb_incomp_if2.vcd
$date
	Thu Jun  3 10:12:41 2021
$end
$version
	Icarus Verilog
$end
$timescale
	1ps
$end
$scope module tb_incomp_if2 $end
$var wire 1 ! y $end
$var reg 1 " i0 $end
$var reg 1 # i1 $end
$var reg 1 $ i2 $end
$var reg 1 % i3 $end
$scope module uut $end
$var wire 1 " i0 $end
$var wire 1 # i1 $end
$var wire 1 $ i2 $end
$var wire 1 % i3 $end
$var reg 1 ! y $end
$upscope $end
$upscope $end
$enddefinitions $end
#0
$dumpvars
0%
0$
0#
0"
x!
$end
#37000
1#
#67000
1%
#74000
0#
#111000
1#
#134000
0%
#148000
0#
#157000
0!
1$
#185000
1#
#201000
1!
1%
#222000
0#
#259000
1#
#268000
0!
0%
#296000
0#
#314000
0$
#317000
1"
#333000
1!
1#
#335000
1%
#370000
0!
0#
#402000
0%
#407000
1!
1#
#444000
0!
0#
#469000
1%
#471000
1$
#481000
1!
1#
#518000
0!
0#
#536000
0%
#555000
1!
1#
#592000
0!
0#
#603000
1%
#628000
0$
#629000
1!
1#
#634000
0"
#666000
0#
#670000
0%
#703000
1#
#737000
1%
#740000
0#
#777000
1#
#785000
1$
#804000
0!
0%
#814000
0#
#851000
1#
#871000
1!
1%
#888000
0#
#925000
1#
#938000
0!
0%
#942000
0$
#951000
1!
1"
#962000
0!
0#
#999000
1!
1#
#1005000
1%
#1036000
0!
0#
#1072000
0%
#1073000
1!
1#
#1099000
1$
#1110000
0!
0#
#1139000
1%
#1147000
1!
1#
#1184000
0!
0#
#1206000
0%
#1221000
1!
1#
#1256000
0$
#1258000
0!
0#
#1268000
0"
#1273000
1%
#1295000
1#
#1332000
0#
#1340000
0%
#1369000
1#
#1406000
0#
#1407000
1%
#1413000
1!
1$
#1443000
1#
#1474000
0!
0%
#1480000
0#
#1517000
1#
#1541000
1!
1%
#1554000
0#
#1570000
0$
#1585000
0!
1"
#1591000
1!
1#
#1608000
0%
#1628000
0!
0#
#1665000
1!
1#
#1675000
1%
#1702000
0!
0#
#1727000
1$
#1739000
1!
1#
#1742000
0%
#1776000
0!
0#
#1809000
1%
#1813000
1!
1#
#1850000
0!
0#
#1876000
0%
#1884000
0$
#1887000
1!
1#
#1902000
0"
#1924000
0#
#1943000
1%
#1961000
1#
#1998000
0#
#2010000
0%
#2035000
1#
#2041000
0!
1$
#2072000
0#
#2077000
1!
1%
#2109000
1#
#2144000
0!
0%
#2146000
0#
#2183000
1#
#2198000
0$
#2211000
1%
#2219000
1!
1"
#2220000
0!
0#
#2257000
1!
1#
#2278000
0%
#2294000
0!
0#
#2331000
1!
1#
#2345000
1%
#2355000
1$
#2368000
0!
0#
#2405000
1!
1#
#2412000
0%
#2442000
0!
0#
#2479000
1!
1#
1%
#2512000
0$
#2516000
0!
0#
#2536000
0"
#2546000
0%
#2553000
1#
#2590000
0#
#2613000
1%
#2627000
1#
#2664000
0#
#2669000
1!
1$
#2680000
0!
0%
#2701000
1#
#2738000
0#
#2747000
1!
1%
#2775000
1#
#2812000
0#
#2814000
0!
0%
#2826000
0$
#2849000
1#
#2853000
1!
1"
#2881000
1%
#2886000
0!
0#
#2923000
1!
1#
#2948000
0%
#2960000
0!
0#
#2983000
1$
#2997000
1!
1#
