Combinational_Logic_Optimization/opt_check2.v
module opt_check2 (
	input 	a , 
	input 	b , 
	output 	y
);
	assign y = a?1:b;
endmodule

Combinational_Logic_Optimization/tb_opt_check2.v
`timescale 1ns / 1ps
module tb_opt_check2;
	// Inputs
	reg a,b;
	// Outputs
	wire y;

        // Instantiate the Unit Under Test (UUT)
	opt_check2 uut (
		.a(a),
		.b(b),
		.y(y)
	);

	initial begin
	$dumpfile("tb_opt_check2.vcd");
	$dumpvars(0,tb_opt_check2);
	// Initialize Inputs
	a = 0;
	b = 0;
	#300 $finish;
	end

	always #10 a = ~a;
	always #55 b = ~b;

endmodule

Combinational_Logic_Optimization/tb_opt_check2.vcd
$date
	Mon May 31 17:55:48 2021
$end
$version
	Icarus Verilog
$end
$timescale
	1ps
$end
$scope module tb_opt_check2 $end
$var wire 1 ! y $end
$var reg 1 " a $end
$var reg 1 # b $end
$scope module uut $end
$var wire 1 " a $end
$var wire 1 # b $end
$var wire 1 ! y $end
$upscope $end
$upscope $end
$enddefinitions $end
#0
$dumpvars
0#
0"
0!
$end
#10000
1!
1"
#20000
0!
0"
#30000
1!
1"
#40000
0!
0"
#50000
1!
1"
#55000
1#
#60000
0"
#70000
1"
#80000
0"
#90000
1"
#100000
0"
#110000
1"
0#
#120000
0!
0"
#130000
1!
1"
#140000
0!
0"
#150000
1!
1"
#160000
0!
0"
#165000
1!
1#
#170000
1"
#180000
0"
#190000
1"
#200000
0"
#210000
1"
#220000
0!
0"
0#
#230000
1!
1"
#240000
0!
0"
#250000
1!
1"
#260000
0!
0"
#270000
1!
1"
#275000
1#
#280000
0"
#290000
1"
#300000
0"
