Unused_Output_Optimization/counter_opt1.v
module counter_opt1 (
	input 	clk , 
	input 	reset , 
	output 	q
);

reg [2:0] count;

assign q = count[0];

always @(posedge clk ,posedge reset)
begin
	if(reset)
		count <= 3'b000;
	else
		count <= count + 1;
end

endmodule

Unused_Output_Optimization/tb_counter_opt1.v
`timescale 1ns / 1ps
module tb_counter_opt1;
	// Inputs
	reg clk, reset   ;
	// Output
	wire q;

        // Instantiate the Unit Under Test (UUT)
	counter_opt1 uut (
		.clk	(clk	),
		.reset	(reset	),
		.q	(q	)
	);

	initial begin
	$dumpfile("tb_counter_opt1.vcd");
	$dumpvars(0,tb_counter_opt1);
	// Initialize Inputs
	clk = 0;
	reset = 1;
	#3000 $finish;
	end

	always #10 clk = ~clk;
	always #1547 reset=~reset;

endmodule

Unused_Output_Optimization/tb_counter_opt1.vcd
$date
	Wed Jun  2 17:20:05 2021
$end
$version
	Icarus Verilog
$end
$timescale
	1ps
$end
$scope module tb_counter_opt1 $end
$var wire 1 ! q $end
$var reg 1 " clk $end
$var reg 1 # reset $end
$scope module uut $end
$var wire 1 " clk $end
$var wire 1 # reset $end
$var wire 1 ! q $end
$var reg 3 $ count [2:0] $end
$upscope $end
$upscope $end
$enddefinitions $end
#0
$dumpvars
b0 $
1#
0"
0!
$end
#10000
1"
#20000
0"
#30000
1"
#40000
0"
#50000
1"
#60000
0"
#70000
1"
#80000
0"
#90000
1"
#100000
0"
#110000
1"
#120000
0"
#130000
1"
#140000
0"
#150000
1"
#160000
0"
#170000
1"
#180000
0"
#190000
1"
#200000
0"
#210000
1"
#220000
0"
#230000
1"
#240000
0"
#250000
1"
#260000
0"
#270000
1"
#280000
0"
#290000
1"
#300000
0"
#310000
1"
#320000
0"
#330000
1"
#340000
0"
#350000
1"
#360000
0"
#370000
1"
#380000
0"
#390000
1"
#400000
0"
#410000
1"
#420000
0"
#430000
1"
#440000
0"
#450000
1"
#460000
0"
#470000
1"
#480000
0"
#490000
1"
#500000
0"
#510000
1"
#520000
0"
#530000
1"
#540000
0"
#550000
1"
#560000
0"
#570000
1"
#580000
0"
#590000
1"
#600000
0"
#610000
1"
#620000
0"
#630000
1"
#640000
0"
#650000
1"
#660000
0"
#670000
1"
#680000
0"
#690000
1"
#700000
0"
#710000
1"
#720000
0"
#730000
1"
#740000
0"
#750000
1"
#760000
0"
#770000
1"
#780000
0"
#790000
1"
#800000
0"
#810000
1"
#820000
0"
#830000
1"
#840000
0"
#850000
1"
#860000
0"
#870000
1"
#880000
0"
#890000
1"
#900000
0"
#910000
1"
#920000
0"
#930000
1"
#940000
0"
#950000
1"
#960000
0"
#970000
1"
#980000
0"
#990000
1"
#1000000
0"
#1010000
1"
#1020000
0"
#1030000
1"
#1040000
0"
#1050000
1"
#1060000
0"
#1070000
1"
#1080000
0"
#1090000
1"
#1100000
0"
#1110000
1"
#1120000
0"
#1130000
1"
#1140000
0"
#1150000
1"
#1160000
0"
#1170000
1"
#1180000
0"
#1190000
1"
#1200000
0"
#1210000
1"
#1220000
0"
#1230000
1"
#1240000
0"
#1250000
1"
#1260000
0"
#1270000
1"
#1280000
0"
#1290000
1"
#1300000
0"
#1310000
1"
#1320000
0"
#1330000
1"
#1340000
0"
#1350000
1"
#1360000
0"
#1370000
1"
#1380000
0"
#1390000
1"
#1400000
0"
#1410000
1"
#1420000
0"
#1430000
1"
#1440000
0"
#1450000
1"
#1460000
0"
#1470000
1"
#1480000
0"
#1490000
1"
#1500000
0"
#1510000
1"
#1520000
0"
#1530000
1"
#1540000
0"
#1547000
0#
#1550000
1!
b1 $
1"
#1560000
0"
#1570000
0!
b10 $
1"
#1580000
0"
#1590000
1!
b11 $
1"
#1600000
0"
#1610000
0!
b100 $
1"
#1620000
0"
#1630000
1!
b101 $
1"
#1640000
0"
#1650000
0!
b110 $
1"
#1660000
0"
#1670000
1!
b111 $
1"
#1680000
0"
#1690000
0!
b0 $
1"
#1700000
0"
#1710000
1!
b1 $
1"
#1720000
0"
#1730000
0!
b10 $
1"
#1740000
0"
#1750000
1!
b11 $
1"
#1760000
0"
#1770000
0!
b100 $
1"
#1780000
0"
#1790000
1!
b101 $
1"
#1800000
0"
#1810000
0!
b110 $
1"
#1820000
0"
#1830000
1!
b111 $
1"
#1840000
0"
#1850000
0!
b0 $
1"
#1860000
0"
#1870000
1!
b1 $
1"
#1880000
0"
#1890000
0!
b10 $
1"
#1900000
0"
#1910000
1!
b11 $
1"
#1920000
0"
#1930000
0!
b100 $
1"
#1940000
0"
#1950000
1!
b101 $
1"
#1960000
0"
#1970000
0!
b110 $
1"
#1980000
0"
#1990000
1!
b111 $
1"
#2000000
0"
#2010000
0!
b0 $
1"
#2020000
0"
#2030000
1!
b1 $
1"
#2040000
0"
#2050000
0!
b10 $
1"
#2060000
0"
#2070000
1!
b11 $
1"
#2080000
0"
#2090000
0!
b100 $
1"
#2100000
0"
#2110000
1!
b101 $
1"
#2120000
0"
#2130000
0!
b110 $
1"
#2140000
0"
#2150000
1!
b111 $
1"
#2160000
0"
#2170000
0!
b0 $
1"
#2180000
0"
#2190000
1!
b1 $
1"
#2200000
0"
#2210000
0!
b10 $
1"
#2220000
0"
#2230000
1!
b11 $
1"
#2240000
0"
#2250000
0!
b100 $
1"
#2260000
0"
#2270000
1!
b101 $
1"
#2280000
0"
#2290000
0!
b110 $
1"
#2300000
0"
#2310000
1!
b111 $
1"
#2320000
0"
#2330000
0!
b0 $
1"
#2340000
0"
#2350000
1!
b1 $
1"
#2360000
0"
#2370000
0!
b10 $
1"
#2380000
0"
#2390000
1!
b11 $
1"
#2400000
0"
#2410000
0!
b100 $
1"
#2420000
0"
#2430000
1!
b101 $
1"
#2440000
0"
#2450000
0!
b110 $
1"
#2460000
0"
#2470000
1!
b111 $
1"
#2480000
0"
#2490000
0!
b0 $
1"
#2500000
0"
#2510000
1!
b1 $
1"
#2520000
0"
#2530000
0!
b10 $
1"
#2540000
0"
#2550000
1!
b11 $
1"
#2560000
0"
#2570000
0!
b100 $
1"
#2580000
0"
#2590000
1!
b101 $
1"
#2600000
0"
#2610000
0!
b110 $
1"
#2620000
0"
#2630000
1!
b111 $
1"
#2640000
0"
#2650000
0!
b0 $
1"
#2660000
0"
#2670000
1!
b1 $
1"
#2680000
0"
#2690000
0!
b10 $
1"
#2700000
0"
#2710000
1!
b11 $
1"
#2720000
0"
#2730000
0!
b100 $
1"
#2740000
0"
#2750000
1!
b101 $
1"
#2760000
0"
#2770000
0!
b110 $
1"
#2780000
0"
#2790000
1!
b111 $
1"
#2800000
0"
#2810000
0!
b0 $
1"
#2820000
0"
#2830000
1!
b1 $
1"
#2840000
0"
#2850000
0!
b10 $
1"
#2860000
0"
#2870000
1!
b11 $
1"
#2880000
0"
#2890000
0!
b100 $
1"
#2900000
0"
#2910000
1!
b101 $
1"
#2920000
0"
#2930000
0!
b110 $
1"
#2940000
0"
#2950000
1!
b111 $
1"
#2960000
0"
#2970000
0!
b0 $
1"
#2980000
0"
#2990000
1!
b1 $
1"
