for_and_for_generate/demux_for.v
module demux_for (
	output 		o0 , 
	output 		o1 , 
	output 		o2 , 
	output 		o3 , 
	output 		o4 , 
	output 		o5 , 
	output 		o6 , 
	output 		o7 , 
	input 	[2:0] 	sel , 
	input 		i
);

reg [7:0]y_int;
assign {o7,o6,o5,o4,o3,o2,o1,o0} = y_int;
integer k;

always @ (*)
	begin
	y_int = 8'b0;
	for(k = 0; k < 8; k=k+1) begin
		if(k == sel)
			y_int[k] = i;
	end
end

endmodule

for_and_for_generate/tb_demux_for.v
`timescale 1ns / 1ps
module tb_demux_for;
	// Inputs
	reg i;
	reg [2:0] sel;
	
	//TB Signals
	reg clk,reset;

	// Outputs
	wire o7,o6,o5,o4,o3,o2,o1,o0;

        // Instantiate the Unit Under Test (UUT)
	demux_for uut (
		.sel(sel),
		.o0(o0),
		.o1(o1),
		.o2(o2),
		.o3(o3),
		.o4(o4),
		.o5(o5),
		.o6(o6),
		.o7(o7),
		.i(i)
	);

	initial begin
	$dumpfile("tb_demux_for.vcd");
	$dumpvars(0,tb_demux_for);
	// Initialize Inputs
	i = 1'b0;
	clk = 1'b0;
	reset = 1'b0 ;  #1;
	reset = 1'b1 ;  #10;
	reset = 1'b0;

	#3900 $finish;
	end

always #17 i = ~i;
always #300 clk = ~clk;

always @ (posedge clk , posedge reset)
begin
	if(reset)
		sel <= 3'b000;
	else
		sel <= sel + 1;
end

endmodule

for_and_for_generate/tb_demux_for.vcd
$date
	Sat Jun  5 13:14:39 2021
$end
$version
	Icarus Verilog
$end
$timescale
	1ps
$end
$scope module tb_demux_for $end
$var wire 1 ! o7 $end
$var wire 1 " o6 $end
$var wire 1 # o5 $end
$var wire 1 $ o4 $end
$var wire 1 % o3 $end
$var wire 1 & o2 $end
$var wire 1 ' o1 $end
$var wire 1 ( o0 $end
$var reg 1 ) clk $end
$var reg 1 * i $end
$var reg 1 + reset $end
$var reg 3 , sel [2:0] $end
$scope module uut $end
$var wire 1 * i $end
$var wire 3 - sel [2:0] $end
$var wire 1 ! o7 $end
$var wire 1 " o6 $end
$var wire 1 # o5 $end
$var wire 1 $ o4 $end
$var wire 1 % o3 $end
$var wire 1 & o2 $end
$var wire 1 ' o1 $end
$var wire 1 ( o0 $end
$var reg 8 . y_int [7:0] $end
$var integer 32 / k [31:0] $end
$upscope $end
$upscope $end
$enddefinitions $end
#0
$dumpvars
b1000 /
b0 .
bx -
bx ,
0+
0*
0)
0(
0'
0&
0%
0$
0#
0"
0!
$end
#1000
b1000 /
b0 ,
b0 -
1+
#11000
0+
#17000
1(
b1 .
b1000 /
1*
#34000
0(
b1000 /
b0 .
0*
#51000
1(
b1 .
b1000 /
1*
#68000
0(
b1000 /
b0 .
0*
#85000
1(
b1 .
b1000 /
1*
#102000
0(
b1000 /
b0 .
0*
#119000
1(
b1 .
b1000 /
1*
#136000
0(
b1000 /
b0 .
0*
#153000
1(
b1 .
b1000 /
1*
#170000
0(
b1000 /
b0 .
0*
#187000
1(
b1 .
b1000 /
1*
#204000
0(
b1000 /
b0 .
0*
#221000
1(
b1 .
b1000 /
1*
#238000
0(
b1000 /
b0 .
0*
#255000
1(
b1 .
b1000 /
1*
#272000
0(
b1000 /
b0 .
0*
#289000
1(
b1 .
b1000 /
1*
#300000
1'
0(
b1000 /
b10 .
b1 ,
b1 -
1)
#306000
0'
b1000 /
b0 .
0*
#323000
1'
b10 .
b1000 /
1*
#340000
0'
b1000 /
b0 .
0*
#357000
1'
b10 .
b1000 /
1*
#374000
0'
b1000 /
b0 .
0*
#391000
1'
b10 .
b1000 /
1*
#408000
0'
b1000 /
b0 .
0*
#425000
1'
b10 .
b1000 /
1*
#442000
0'
b1000 /
b0 .
0*
#459000
1'
b10 .
b1000 /
1*
#476000
0'
b1000 /
b0 .
0*
#493000
1'
b10 .
b1000 /
1*
#510000
0'
b1000 /
b0 .
0*
#527000
1'
b10 .
b1000 /
1*
#544000
0'
b1000 /
b0 .
0*
#561000
1'
b10 .
b1000 /
1*
#578000
0'
b1000 /
b0 .
0*
#595000
1'
b10 .
b1000 /
1*
#600000
0)
#612000
0'
b1000 /
b0 .
0*
#629000
1'
b10 .
b1000 /
1*
#646000
0'
b1000 /
b0 .
0*
#663000
1'
b10 .
b1000 /
1*
#680000
0'
b1000 /
b0 .
0*
#697000
1'
b10 .
b1000 /
1*
#714000
0'
b1000 /
b0 .
0*
#731000
1'
b10 .
b1000 /
1*
#748000
0'
b1000 /
b0 .
0*
#765000
1'
b10 .
b1000 /
1*
#782000
0'
b1000 /
b0 .
0*
#799000
1'
b10 .
b1000 /
1*
#816000
0'
b1000 /
b0 .
0*
#833000
1'
b10 .
b1000 /
1*
#850000
0'
b1000 /
b0 .
0*
#867000
1'
b10 .
b1000 /
1*
#884000
0'
b1000 /
b0 .
0*
#900000
b1000 /
b10 ,
b10 -
1)
#901000
1&
b100 .
b1000 /
1*
#918000
0&
b1000 /
b0 .
0*
#935000
1&
b100 .
b1000 /
1*
#952000
0&
b1000 /
b0 .
0*
#969000
1&
b100 .
b1000 /
1*
#986000
0&
b1000 /
b0 .
0*
#1003000
1&
b100 .
b1000 /
1*
#1020000
0&
b1000 /
b0 .
0*
#1037000
1&
b100 .
b1000 /
1*
#1054000
0&
b1000 /
b0 .
0*
#1071000
1&
b100 .
b1000 /
1*
#1088000
0&
b1000 /
b0 .
0*
#1105000
1&
b100 .
b1000 /
1*
#1122000
0&
b1000 /
b0 .
0*
#1139000
1&
b100 .
b1000 /
1*
#1156000
0&
b1000 /
b0 .
0*
#1173000
1&
b100 .
b1000 /
1*
#1190000
0&
b1000 /
b0 .
0*
#1200000
0)
#1207000
1&
b100 .
b1000 /
1*
#1224000
0&
b1000 /
b0 .
0*
#1241000
1&
b100 .
b1000 /
1*
#1258000
0&
b1000 /
b0 .
0*
#1275000
1&
b100 .
b1000 /
1*
#1292000
0&
b1000 /
b0 .
0*
#1309000
1&
b100 .
b1000 /
1*
#1326000
0&
b1000 /
b0 .
0*
#1343000
1&
b100 .
b1000 /
1*
#1360000
0&
b1000 /
b0 .
0*
#1377000
1&
b100 .
b1000 /
1*
#1394000
0&
b1000 /
b0 .
0*
#1411000
1&
b100 .
b1000 /
1*
#1428000
0&
b1000 /
b0 .
0*
#1445000
1&
b100 .
b1000 /
1*
#1462000
0&
b1000 /
b0 .
0*
#1479000
1&
b100 .
b1000 /
1*
#1496000
0&
b1000 /
b0 .
0*
#1500000
b1000 /
b11 ,
b11 -
1)
#1513000
1%
b1000 .
b1000 /
1*
#1530000
0%
b1000 /
b0 .
0*
#1547000
1%
b1000 .
b1000 /
1*
#1564000
0%
b1000 /
b0 .
0*
#1581000
1%
b1000 .
b1000 /
1*
#1598000
0%
b1000 /
b0 .
0*
#1615000
1%
b1000 .
b1000 /
1*
#1632000
0%
b1000 /
b0 .
0*
#1649000
1%
b1000 .
b1000 /
1*
#1666000
0%
b1000 /
b0 .
0*
#1683000
1%
b1000 .
b1000 /
1*
#1700000
0%
b1000 /
b0 .
0*
#1717000
1%
b1000 .
b1000 /
1*
#1734000
0%
b1000 /
b0 .
0*
#1751000
1%
b1000 .
b1000 /
1*
#1768000
0%
b1000 /
b0 .
0*
#1785000
1%
b1000 .
b1000 /
1*
#1800000
0)
#1802000
0%
b1000 /
b0 .
0*
#1819000
1%
b1000 .
b1000 /
1*
#1836000
0%
b1000 /
b0 .
0*
#1853000
1%
b1000 .
b1000 /
1*
#1870000
0%
b1000 /
b0 .
0*
#1887000
1%
b1000 .
b1000 /
1*
#1904000
0%
b1000 /
b0 .
0*
#1921000
1%
b1000 .
b1000 /
1*
#1938000
0%
b1000 /
b0 .
0*
#1955000
1%
b1000 .
b1000 /
1*
#1972000
0%
b1000 /
b0 .
0*
#1989000
1%
b1000 .
b1000 /
1*
#2006000
0%
b1000 /
b0 .
0*
#2023000
1%
b1000 .
b1000 /
1*
#2040000
0%
b1000 /
b0 .
0*
#2057000
1%
b1000 .
b1000 /
1*
#2074000
0%
b1000 /
b0 .
0*
#2091000
1%
b1000 .
b1000 /
1*
#2100000
1$
0%
b1000 /
b10000 .
b100 ,
b100 -
1)
#2108000
0$
b1000 /
b0 .
0*
#2125000
1$
b10000 .
b1000 /
1*
#2142000
0$
b1000 /
b0 .
0*
#2159000
1$
b10000 .
b1000 /
1*
#2176000
0$
b1000 /
b0 .
0*
#2193000
1$
b10000 .
b1000 /
1*
#2210000
0$
b1000 /
b0 .
0*
#2227000
1$
b10000 .
b1000 /
1*
#2244000
0$
b1000 /
b0 .
0*
#2261000
1$
b10000 .
b1000 /
1*
#2278000
0$
b1000 /
b0 .
0*
#2295000
1$
b10000 .
b1000 /
1*
#2312000
0$
b1000 /
b0 .
0*
#2329000
1$
b10000 .
b1000 /
1*
#2346000
0$
b1000 /
b0 .
0*
#2363000
1$
b10000 .
b1000 /
1*
#2380000
0$
b1000 /
b0 .
0*
#2397000
1$
b10000 .
b1000 /
1*
#2400000
0)
#2414000
0$
b1000 /
b0 .
0*
#2431000
1$
b10000 .
b1000 /
1*
#2448000
0$
b1000 /
b0 .
0*
#2465000
1$
b10000 .
b1000 /
1*
#2482000
0$
b1000 /
b0 .
0*
#2499000
1$
b10000 .
b1000 /
1*
#2516000
0$
b1000 /
b0 .
0*
#2533000
1$
b10000 .
b1000 /
1*
#2550000
0$
b1000 /
b0 .
0*
#2567000
1$
b10000 .
b1000 /
1*
#2584000
0$
b1000 /
b0 .
0*
#2601000
1$
b10000 .
b1000 /
1*
#2618000
0$
b1000 /
b0 .
0*
#2635000
1$
b10000 .
b1000 /
1*
#2652000
0$
b1000 /
b0 .
0*
#2669000
1$
b10000 .
b1000 /
1*
#2686000
0$
b1000 /
b0 .
0*
#2700000
b1000 /
b101 ,
b101 -
1)
#2703000
1#
b100000 .
b1000 /
1*
#2720000
0#
b1000 /
b0 .
0*
#2737000
1#
b100000 .
b1000 /
1*
#2754000
0#
b1000 /
b0 .
0*
#2771000
1#
b100000 .
b1000 /
1*
#2788000
0#
b1000 /
b0 .
0*
#2805000
1#
b100000 .
b1000 /
1*
#2822000
0#
b1000 /
b0 .
0*
#2839000
1#
b100000 .
b1000 /
1*
#2856000
0#
b1000 /
b0 .
0*
#2873000
1#
b100000 .
b1000 /
1*
#2890000
0#
b1000 /
b0 .
0*
#2907000
1#
b100000 .
b1000 /
1*
#2924000
0#
b1000 /
b0 .
0*
#2941000
1#
b100000 .
b1000 /
1*
#2958000
0#
b1000 /
b0 .
0*
#2975000
1#
b100000 .
b1000 /
1*
#2992000
0#
b1000 /
b0 .
0*
#3000000
0)
#3009000
1#
b100000 .
b1000 /
1*
#3026000
0#
b1000 /
b0 .
0*
#3043000
1#
b100000 .
b1000 /
1*
#3060000
0#
b1000 /
b0 .
0*
#3077000
1#
b100000 .
b1000 /
1*
#3094000
0#
b1000 /
b0 .
0*
#3111000
1#
b100000 .
b1000 /
1*
#3128000
0#
b1000 /
b0 .
0*
#3145000
1#
b100000 .
b1000 /
1*
#3162000
0#
b1000 /
b0 .
0*
#3179000
1#
b100000 .
b1000 /
1*
#3196000
0#
b1000 /
b0 .
0*
#3213000
1#
b100000 .
b1000 /
1*
#3230000
0#
b1000 /
b0 .
0*
#3247000
1#
b100000 .
b1000 /
1*
#3264000
0#
b1000 /
b0 .
0*
#3281000
1#
b100000 .
b1000 /
1*
#3298000
0#
b1000 /
b0 .
0*
#3300000
b1000 /
b110 ,
b110 -
1)
#3315000
1"
b1000000 .
b1000 /
1*
#3332000
0"
b1000 /
b0 .
0*
#3349000
1"
b1000000 .
b1000 /
1*
#3366000
0"
b1000 /
b0 .
0*
#3383000
1"
b1000000 .
b1000 /
1*
#3400000
0"
b1000 /
b0 .
0*
#3417000
1"
b1000000 .
b1000 /
1*
#3434000
0"
b1000 /
b0 .
0*
#3451000
1"
b1000000 .
b1000 /
1*
#3468000
0"
b1000 /
b0 .
0*
#3485000
1"
b1000000 .
b1000 /
1*
#3502000
0"
b1000 /
b0 .
0*
#3519000
1"
b1000000 .
b1000 /
1*
#3536000
0"
b1000 /
b0 .
0*
#3553000
1"
b1000000 .
b1000 /
1*
#3570000
0"
b1000 /
b0 .
0*
#3587000
1"
b1000000 .
b1000 /
1*
#3600000
0)
#3604000
0"
b1000 /
b0 .
0*
#3621000
1"
b1000000 .
b1000 /
1*
#3638000
0"
b1000 /
b0 .
0*
#3655000
1"
b1000000 .
b1000 /
1*
#3672000
0"
b1000 /
b0 .
0*
#3689000
1"
b1000000 .
b1000 /
1*
#3706000
0"
b1000 /
b0 .
0*
#3723000
1"
b1000000 .
b1000 /
1*
#3740000
0"
b1000 /
b0 .
0*
#3757000
1"
b1000000 .
b1000 /
1*
#3774000
0"
b1000 /
b0 .
0*
#3791000
1"
b1000000 .
b1000 /
1*
#3808000
0"
b1000 /
b0 .
0*
#3825000
1"
b1000000 .
b1000 /
1*
#3842000
0"
b1000 /
b0 .
0*
#3859000
1"
b1000000 .
b1000 /
1*
#3876000
0"
b1000 /
b0 .
0*
#3893000
1"
b1000000 .
b1000 /
1*
#3900000
1!
0"
b1000 /
b10000000 .
b111 ,
b111 -
1)
#3910000
0!
b1000 /
b0 .
0*
