for_and_for_generate/mux_for.v
module mux_for (
	input 			i0 , 
	input 			i1 , 
	input 			i2 , 
	input 			i3 , 
	input 	[1:0] 		sel, 
	output 	 	reg	y
);


wire [3:0] i_int;
assign i_int = {i3,i2,i1,i0};
integer k;

always @ (*)
	begin
	y = 0;
	for(k = 0; k < 4; k=k+1) begin
		if(k == sel)
			y = i_int[k];
	end
end

endmodule

for_and_for_generate/tb_mux_for.v
`timescale 1ns / 1ps
module tb_mux_for;
	// Inputs
	reg i0,i1;
	reg i2,i3;
	reg [1:0] sel;
	
	//TB Signals
	reg clk,reset;

	// Outputs
	wire y;

        // Instantiate the Unit Under Test (UUT)
	mux_for uut (
		.sel(sel),
		.i0(i0),
		.i1(i1),
		.i2(i2),
		.i3(i3),
		.y(y)
	);

	initial begin
	$dumpfile("tb_mux_for.vcd");
	$dumpvars(0,tb_mux_for);
	// Initialize Inputs
	i0 = 1'b0;
	i1 = 1'b0;
	i2 = 1'b0;
	i3 = 1'b0;
	clk = 1'b0;
	reset = 1'b0 ;  #1;
	reset = 1'b1 ;  #10;
	reset = 1'b0;

	#3000 $finish;
	end

always #17 i0 = ~i0;
always #37 i1 = ~i1;
always #88 i2 = ~i2;
always #155 i3 = ~i3;
always #300 clk = ~clk;

always @ (posedge clk , posedge reset)
begin
	if(reset)
		sel <= 2'b00;
	else
		sel <= sel + 1;
end

endmodule

for_and_for_generate/tb_mux_for.vcd
$date
	Sat Jun  5 19:55:16 2021
$end
$version
	Icarus Verilog
$end
$timescale
	1ps
$end
$scope module tb_mux_for $end
$var wire 1 ! y $end
$var reg 1 " clk $end
$var reg 1 # i0 $end
$var reg 1 $ i1 $end
$var reg 1 % i2 $end
$var reg 1 & i3 $end
$var reg 1 ' reset $end
$var reg 2 ( sel [1:0] $end
$scope module uut $end
$var wire 1 # i0 $end
$var wire 1 $ i1 $end
$var wire 1 % i2 $end
$var wire 1 & i3 $end
$var wire 2 ) sel [1:0] $end
$var wire 4 * i_int [3:0] $end
$var reg 1 ! y $end
$var integer 32 + k [31:0] $end
$upscope $end
$upscope $end
$enddefinitions $end
#0
$dumpvars
b100 +
b0 *
bx )
bx (
0'
0&
0%
0$
0#
0"
0!
$end
#1000
b100 +
b0 (
b0 )
1'
#11000
0'
#17000
1!
b100 +
b1 *
1#
#34000
b100 +
0!
b0 *
0#
#37000
b100 +
b10 *
1$
#51000
1!
b100 +
b11 *
1#
#68000
b100 +
0!
b10 *
0#
#74000
b100 +
b0 *
0$
#85000
1!
b100 +
b1 *
1#
#88000
b100 +
1!
b101 *
1%
#102000
b100 +
0!
b100 *
0#
#111000
b100 +
b110 *
1$
#119000
1!
b100 +
b111 *
1#
#136000
b100 +
0!
b110 *
0#
#148000
b100 +
b100 *
0$
#153000
1!
b100 +
b101 *
1#
#155000
b100 +
1!
b1101 *
1&
#170000
b100 +
0!
b1100 *
0#
#176000
b100 +
b1000 *
0%
#185000
b100 +
b1010 *
1$
#187000
1!
b100 +
b1011 *
1#
#204000
b100 +
0!
b1010 *
0#
#221000
1!
b100 +
b1011 *
1#
#222000
b100 +
1!
b1001 *
0$
#238000
b100 +
0!
b1000 *
0#
#255000
1!
b100 +
b1001 *
1#
#259000
b100 +
1!
b1011 *
1$
#264000
b100 +
1!
b1111 *
1%
#272000
b100 +
0!
b1110 *
0#
#289000
1!
b100 +
b1111 *
1#
#296000
b100 +
1!
b1101 *
0$
#300000
b100 +
0!
b1 (
b1 )
1"
#306000
b100 +
b1100 *
0#
#310000
b100 +
b100 *
0&
#323000
b100 +
b101 *
1#
#333000
1!
b100 +
b111 *
1$
#340000
b100 +
1!
b110 *
0#
#352000
b100 +
1!
b10 *
0%
#357000
b100 +
1!
b11 *
1#
#370000
b100 +
0!
b1 *
0$
#374000
b100 +
b0 *
0#
#391000
b100 +
b1 *
1#
#407000
1!
b100 +
b11 *
1$
#408000
b100 +
1!
b10 *
0#
#425000
b100 +
1!
b11 *
1#
#440000
b100 +
1!
b111 *
1%
#442000
b100 +
1!
b110 *
0#
#444000
b100 +
0!
b100 *
0$
#459000
b100 +
b101 *
1#
#465000
b100 +
b1101 *
1&
#476000
b100 +
b1100 *
0#
#481000
1!
b100 +
b1110 *
1$
#493000
b100 +
1!
b1111 *
1#
#510000
b100 +
1!
b1110 *
0#
#518000
b100 +
0!
b1100 *
0$
#527000
b100 +
b1101 *
1#
#528000
b100 +
b1001 *
0%
#544000
b100 +
b1000 *
0#
#555000
1!
b100 +
b1010 *
1$
#561000
b100 +
1!
b1011 *
1#
#578000
b100 +
1!
b1010 *
0#
#592000
b100 +
0!
b1000 *
0$
#595000
b100 +
b1001 *
1#
#600000
0"
#612000
b100 +
b1000 *
0#
#616000
b100 +
b1100 *
1%
#620000
b100 +
b100 *
0&
#629000
1!
b100 +
1#
b111 *
1$
#646000
b100 +
1!
b110 *
0#
#663000
b100 +
1!
b111 *
1#
#666000
b100 +
0!
b101 *
0$
#680000
b100 +
b100 *
0#
#697000
b100 +
b101 *
1#
#703000
1!
b100 +
b111 *
1$
#704000
b100 +
1!
b11 *
0%
#714000
b100 +
1!
b10 *
0#
#731000
b100 +
1!
b11 *
1#
#740000
b100 +
0!
b1 *
0$
#748000
b100 +
b0 *
0#
#765000
b100 +
b1 *
1#
#775000
b100 +
b1001 *
1&
#777000
1!
b100 +
b1011 *
1$
#782000
b100 +
1!
b1010 *
0#
#792000
b100 +
1!
b1110 *
1%
#799000
b100 +
1!
b1111 *
1#
#814000
b100 +
0!
b1101 *
0$
#816000
b100 +
b1100 *
0#
#833000
b100 +
b1101 *
1#
#850000
b100 +
b1100 *
0#
#851000
1!
b100 +
b1110 *
1$
#867000
b100 +
1!
b1111 *
1#
#880000
b100 +
1!
b1011 *
0%
#884000
b100 +
1!
b1010 *
0#
#888000
b100 +
0!
b1000 *
0$
#900000
b100 +
b10 (
b10 )
1"
#901000
b100 +
b1001 *
1#
#918000
b100 +
b1000 *
0#
#925000
b100 +
b1010 *
1$
#930000
b100 +
b10 *
0&
#935000
b100 +
b11 *
1#
#952000
b100 +
b10 *
0#
#962000
b100 +
b0 *
0$
#968000
1!
b100 +
b100 *
1%
#969000
b100 +
1!
b101 *
1#
#986000
b100 +
1!
b100 *
0#
#999000
b100 +
1!
b110 *
1$
#1003000
b100 +
1!
b111 *
1#
#1020000
b100 +
1!
b110 *
0#
#1036000
b100 +
1!
b100 *
0$
#1037000
b100 +
1!
b101 *
1#
#1054000
b100 +
1!
b100 *
0#
#1056000
b100 +
0!
b0 *
0%
#1071000
b100 +
b1 *
1#
#1073000
b100 +
b11 *
1$
#1085000
b100 +
b1011 *
1&
#1088000
b100 +
b1010 *
0#
#1105000
b100 +
b1011 *
1#
#1110000
b100 +
b1001 *
0$
#1122000
b100 +
b1000 *
0#
#1139000
b100 +
b1001 *
1#
#1144000
1!
b100 +
b1101 *
1%
#1147000
b100 +
1!
b1111 *
1$
#1156000
b100 +
1!
b1110 *
0#
#1173000
b100 +
1!
b1111 *
1#
#1184000
b100 +
1!
b1101 *
0$
#1190000
b100 +
1!
b1100 *
0#
#1200000
0"
#1207000
b100 +
1!
b1101 *
1#
#1221000
b100 +
1!
b1111 *
1$
#1224000
b100 +
1!
b1110 *
0#
#1232000
b100 +
0!
b1010 *
0%
#1240000
b100 +
b10 *
0&
#1241000
b100 +
b11 *
1#
#1258000
b100 +
0#
b0 *
0$
#1275000
b100 +
b1 *
1#
#1292000
b100 +
b0 *
0#
#1295000
b100 +
b10 *
1$
#1309000
b100 +
b11 *
1#
#1320000
1!
b100 +
b111 *
1%
#1326000
b100 +
1!
b110 *
0#
#1332000
b100 +
1!
b100 *
0$
#1343000
b100 +
1!
b101 *
1#
#1360000
b100 +
1!
b100 *
0#
#1369000
b100 +
1!
b110 *
1$
#1377000
b100 +
1!
b111 *
1#
#1394000
b100 +
1!
b110 *
0#
#1395000
b100 +
1!
b1110 *
1&
#1406000
b100 +
1!
b1100 *
0$
#1408000
b100 +
0!
b1000 *
0%
#1411000
b100 +
b1001 *
1#
#1428000
b100 +
b1000 *
0#
#1443000
b100 +
b1010 *
1$
#1445000
b100 +
b1011 *
1#
#1462000
b100 +
b1010 *
0#
#1479000
b100 +
b1011 *
1#
#1480000
b100 +
b1001 *
0$
#1496000
1!
b100 +
0#
b1100 *
1%
#1500000
b100 +
1!
b11 (
b11 )
1"
#1513000
b100 +
1!
b1101 *
1#
#1517000
b100 +
1!
b1111 *
1$
#1530000
b100 +
1!
b1110 *
0#
#1547000
b100 +
1!
b1111 *
1#
#1550000
b100 +
0!
b111 *
0&
#1554000
b100 +
b101 *
0$
#1564000
b100 +
b100 *
0#
#1581000
b100 +
b101 *
1#
#1584000
b100 +
b1 *
0%
#1591000
b100 +
b11 *
1$
#1598000
b100 +
b10 *
0#
#1615000
b100 +
b11 *
1#
#1628000
b100 +
b1 *
0$
#1632000
b100 +
b0 *
0#
#1649000
b100 +
b1 *
1#
#1665000
b100 +
b11 *
1$
#1666000
b100 +
b10 *
0#
#1672000
b100 +
b110 *
1%
#1683000
b100 +
b111 *
1#
#1700000
b100 +
b110 *
0#
#1702000
b100 +
b100 *
0$
#1705000
1!
b100 +
b1100 *
1&
#1717000
b100 +
1!
b1101 *
1#
#1734000
b100 +
1!
b1100 *
0#
#1739000
b100 +
1!
b1110 *
1$
#1751000
b100 +
1!
b1111 *
1#
#1760000
b100 +
1!
b1011 *
0%
#1768000
b100 +
1!
b1010 *
0#
#1776000
b100 +
1!
b1000 *
0$
#1785000
b100 +
1!
b1001 *
1#
#1800000
0"
#1802000
b100 +
1!
b1000 *
0#
#1813000
b100 +
1!
b1010 *
1$
#1819000
b100 +
1!
b1011 *
1#
#1836000
b100 +
1!
b1010 *
0#
#1848000
b100 +
1!
b1110 *
1%
#1850000
b100 +
1!
b1100 *
0$
#1853000
b100 +
1!
b1101 *
1#
#1860000
b100 +
0!
b101 *
0&
#1870000
b100 +
b100 *
0#
#1887000
b100 +
1#
b111 *
1$
#1904000
b100 +
b110 *
0#
#1921000
b100 +
b111 *
1#
#1924000
b100 +
b101 *
0$
#1936000
b100 +
b1 *
0%
#1938000
b100 +
b0 *
0#
#1955000
b100 +
b1 *
1#
#1961000
b100 +
b11 *
1$
#1972000
b100 +
b10 *
0#
#1989000
b100 +
b11 *
1#
#1998000
b100 +
b1 *
0$
#2006000
b100 +
b0 *
0#
#2015000
1!
b100 +
b1000 *
1&
#2023000
b100 +
1!
b1001 *
1#
#2024000
b100 +
1!
b1101 *
1%
#2035000
b100 +
1!
b1111 *
1$
#2040000
b100 +
1!
b1110 *
0#
#2057000
b100 +
1!
b1111 *
1#
#2072000
b100 +
1!
b1101 *
0$
#2074000
b100 +
1!
b1100 *
0#
#2091000
b100 +
1!
b1101 *
1#
#2100000
b100 +
1!
b0 (
b0 )
1"
#2108000
b100 +
0!
b1100 *
0#
#2109000
b100 +
b1110 *
1$
#2112000
b100 +
b1010 *
0%
#2125000
1!
b100 +
b1011 *
1#
#2142000
b100 +
0!
b1010 *
0#
#2146000
b100 +
b1000 *
0$
#2159000
1!
b100 +
b1001 *
1#
#2170000
b100 +
1!
b1 *
0&
#2176000
b100 +
0!
b0 *
0#
#2183000
b100 +
b10 *
1$
#2193000
1!
b100 +
b11 *
1#
#2200000
b100 +
1!
b111 *
1%
#2210000
b100 +
0!
b110 *
0#
#2220000
b100 +
b100 *
0$
#2227000
1!
b100 +
b101 *
1#
#2244000
b100 +
0!
b100 *
0#
#2257000
b100 +
b110 *
1$
#2261000
1!
b100 +
b111 *
1#
#2278000
b100 +
0!
b110 *
0#
#2288000
b100 +
b10 *
0%
#2294000
b100 +
b0 *
0$
#2295000
1!
b100 +
b1 *
1#
#2312000
b100 +
0!
b0 *
0#
#2325000
b100 +
b1000 *
1&
#2329000
1!
b100 +
b1001 *
1#
#2331000
b100 +
1!
b1011 *
1$
#2346000
b100 +
0!
b1010 *
0#
#2363000
1!
b100 +
b1011 *
1#
#2368000
b100 +
1!
b1001 *
0$
#2376000
b100 +
1!
b1101 *
1%
#2380000
b100 +
0!
b1100 *
0#
#2397000
1!
b100 +
b1101 *
1#
#2400000
0"
#2405000
b100 +
1!
b1111 *
1$
#2414000
b100 +
0!
b1110 *
0#
#2431000
1!
b100 +
b1111 *
1#
#2442000
b100 +
1!
b1101 *
0$
#2448000
b100 +
0!
b1100 *
0#
#2464000
b100 +
b1000 *
0%
#2465000
1!
b100 +
b1001 *
1#
#2479000
b100 +
1!
b1011 *
1$
#2480000
b100 +
1!
b11 *
0&
#2482000
b100 +
0!
b10 *
0#
#2499000
1!
b100 +
b11 *
1#
#2516000
b100 +
0!
0#
b0 *
0$
#2533000
1!
b100 +
b1 *
1#
#2550000
b100 +
0!
b0 *
0#
#2552000
b100 +
b100 *
1%
#2553000
b100 +
b110 *
1$
#2567000
1!
b100 +
b111 *
1#
#2584000
b100 +
0!
b110 *
0#
#2590000
b100 +
b100 *
0$
#2601000
1!
b100 +
b101 *
1#
#2618000
b100 +
0!
b100 *
0#
#2627000
b100 +
b110 *
1$
#2635000
1!
b100 +
1#
b1111 *
1&
#2640000
b100 +
1!
b1011 *
0%
#2652000
b100 +
0!
b1010 *
0#
#2664000
b100 +
b1000 *
0$
#2669000
1!
b100 +
b1001 *
1#
#2686000
b100 +
0!
b1000 *
0#
#2700000
b100 +
b1 (
b1 )
1"
#2701000
1!
b100 +
b1010 *
1$
#2703000
b100 +
1!
b1011 *
1#
#2720000
b100 +
1!
b1010 *
0#
#2728000
b100 +
1!
b1110 *
1%
#2737000
b100 +
1!
b1111 *
1#
#2738000
b100 +
0!
b1101 *
0$
#2754000
b100 +
b1100 *
0#
#2771000
b100 +
b1101 *
1#
#2775000
1!
b100 +
b1111 *
1$
#2788000
b100 +
1!
b1110 *
0#
#2790000
b100 +
1!
b110 *
0&
#2805000
b100 +
1!
b111 *
1#
#2812000
b100 +
0!
b101 *
0$
#2816000
b100 +
b1 *
0%
#2822000
b100 +
b0 *
0#
#2839000
b100 +
b1 *
1#
#2849000
1!
b100 +
b11 *
1$
#2856000
b100 +
1!
b10 *
0#
#2873000
b100 +
1!
b11 *
1#
#2886000
b100 +
0!
b1 *
0$
#2890000
b100 +
b0 *
0#
#2904000
b100 +
b100 *
1%
#2907000
b100 +
b101 *
1#
#2923000
1!
b100 +
b111 *
1$
#2924000
b100 +
1!
b110 *
0#
#2941000
b100 +
1!
b111 *
1#
#2945000
b100 +
1!
b1111 *
1&
#2958000
b100 +
1!
b1110 *
0#
#2960000
b100 +
0!
b1100 *
0$
#2975000
b100 +
b1101 *
1#
#2992000
b100 +
0#
b1000 *
0%
#2997000
1!
b100 +
b1010 *
1$
#3000000
0"
#3009000
b100 +
1!
b1011 *
1#
