for_and_for_generate/fa.v
module fa (
	input 	a , 
	input 	b , 
	input 	c , 
	output 	co, 
	output 	sum
);
	assign {co,sum}  = a + b + c ;
endmodule

for_and_for_generate/rca.v
module rca (
	input 	[7:0] 	num1 , 
	input 	[7:0] 	num2 , 
	output 	[8:0] 	sum
);	

wire 	[7:0] 	int_sum;
wire 	[7:0]	int_co;

genvar i;
generate
	for (i = 1 ; i < 8; i=i+1) begin
		fa u_fa_1 (.a(num1[i]),.b(num2[i]),.c(int_co[i-1]),.co(int_co[i]),.sum(int_sum[i]));
	end

endgenerate

fa u_fa_0 (
	.a(num1[0]),
	.b(num2[0]),
	.c(1'b0),
	.co(int_co[0]),
	.sum(int_sum[0])
	);


assign sum[7:0] = int_sum;
assign sum[8] = int_co[7];

endmodule

for_and_for_generate/tb_rca.v
`timescale 1ns / 1ps
module tb_rca;
	// TB_SIGNALS
	reg clk, reset   ;
	reg [7:0] num1 ;
	reg [7:0] num2;
	wire [8:0] sum_out;
	// Instantiate the Unit Under Test (UUT)
	rca uut (
		.num1(num1),
		.num2(num2),
		.sum(sum_out)
	);

	initial begin
	$dumpfile("tb_rca.vcd");
	$dumpvars(0,tb_rca);
	// Initialize Inputs
	clk = 0;
	reset = 0;
	reset = 1; #1;
	reset = 0; #10;
	#30000 $finish;
	end

always #10 clk = ~clk;


always @ (clk,reset)
begin
	if(reset)
	begin
		num1 <= 8'b0;
		num2 <= 8'b0;
	end
	else
	begin
		num1 = num1 + 1;
		if(num1[3:0] == 4'b1111)
			num2 = num2+1;	
	end

end

endmodule

for_and_for_generate/tb_rca.vcd
$date
	Sat Jun  5 20:07:05 2021
$end
$version
	Icarus Verilog
$end
$timescale
	1ps
$end
$scope module tb_rca $end
$var wire 9 ! sum_out [8:0] $end
$var reg 1 " clk $end
$var reg 8 # num1 [7:0] $end
$var reg 8 $ num2 [7:0] $end
$var reg 1 % reset $end
$scope module uut $end
$var wire 8 & num1 [7:0] $end
$var wire 8 ' num2 [7:0] $end
$var wire 9 ( sum [8:0] $end
$var wire 8 ) int_sum [7:0] $end
$var wire 8 * int_co [7:0] $end
$scope begin genblk1[1] $end
$scope module u_fa_1 $end
$var wire 1 + a $end
$var wire 1 , b $end
$var wire 1 - c $end
$var wire 1 . sum $end
$var wire 1 / co $end
$upscope $end
$upscope $end
$scope begin genblk1[2] $end
$scope module u_fa_1 $end
$var wire 1 0 a $end
$var wire 1 1 b $end
$var wire 1 2 c $end
$var wire 1 3 sum $end
$var wire 1 4 co $end
$upscope $end
$upscope $end
$scope begin genblk1[3] $end
$scope module u_fa_1 $end
$var wire 1 5 a $end
$var wire 1 6 b $end
$var wire 1 7 c $end
$var wire 1 8 sum $end
$var wire 1 9 co $end
$upscope $end
$upscope $end
$scope begin genblk1[4] $end
$scope module u_fa_1 $end
$var wire 1 : a $end
$var wire 1 ; b $end
$var wire 1 < c $end
$var wire 1 = sum $end
$var wire 1 > co $end
$upscope $end
$upscope $end
$scope begin genblk1[5] $end
$scope module u_fa_1 $end
$var wire 1 ? a $end
$var wire 1 @ b $end
$var wire 1 A c $end
$var wire 1 B sum $end
$var wire 1 C co $end
$upscope $end
$upscope $end
$scope begin genblk1[6] $end
$scope module u_fa_1 $end
$var wire 1 D a $end
$var wire 1 E b $end
$var wire 1 F c $end
$var wire 1 G sum $end
$var wire 1 H co $end
$upscope $end
$upscope $end
$scope begin genblk1[7] $end
$scope module u_fa_1 $end
$var wire 1 I a $end
$var wire 1 J b $end
$var wire 1 K c $end
$var wire 1 L sum $end
$var wire 1 M co $end
$upscope $end
$upscope $end
$scope module u_fa_0 $end
$var wire 1 N a $end
$var wire 1 O b $end
$var wire 1 P c $end
$var wire 1 Q sum $end
$var wire 1 R co $end
$upscope $end
$upscope $end
$upscope $end
$enddefinitions $end
#0
$dumpvars
0R
0Q
0P
0O
0N
0M
0L
0K
0J
0I
0H
0G
0F
0E
0D
0C
0B
0A
0@
0?
0>
0=
0<
0;
0:
09
08
07
06
05
04
03
02
01
00
0/
0.
0-
0,
0+
b0 *
b0 )
b0 (
b0 '
b0 &
1%
b0 $
b0 #
0"
b0 !
$end
#1000
b1 !
b1 (
b1 )
1Q
1N
b1 #
b1 &
0%
#10000
1.
b10 !
b10 (
b10 )
0Q
1+
0N
b10 #
b10 &
1"
#20000
b11 !
b11 (
b11 )
1Q
1N
b11 #
b11 &
0"
#30000
0.
13
b100 !
b100 (
b100 )
0Q
0+
10
0N
b100 #
b100 &
1"
#40000
b101 !
b101 (
b101 )
1Q
1N
b101 #
b101 &
0"
#50000
1.
b110 !
b110 (
b110 )
0Q
1+
0N
b110 #
b110 &
1"
#60000
b111 !
b111 (
b111 )
1Q
1N
b111 #
b111 &
0"
#70000
0.
03
18
b1000 !
b1000 (
b1000 )
0Q
0+
00
15
0N
b1000 #
b1000 &
1"
#80000
b1001 !
b1001 (
b1001 )
1Q
1N
b1001 #
b1001 &
0"
#90000
1.
b1010 !
b1010 (
b1010 )
0Q
1+
0N
b1010 #
b1010 &
1"
#100000
b1011 !
b1011 (
b1011 )
1Q
1N
b1011 #
b1011 &
0"
#110000
0.
13
b1100 !
b1100 (
b1100 )
0Q
0+
10
0N
b1100 #
b1100 &
1"
#120000
b1101 !
b1101 (
b1101 )
1Q
1N
b1101 #
b1101 &
0"
#130000
1.
b1110 !
b1110 (
b1110 )
0Q
1+
0N
b1110 #
b1110 &
1"
#140000
1=
1<
08
19
17
03
14
12
b10000 !
b10000 (
b10000 )
0.
1/
1-
b1111 *
1R
1O
1N
b1 $
b1 '
b1111 #
b1111 &
0"
#150000
0B
02
07
0<
0A
0-
0.
0/
03
04
08
09
1=
0>
b10001 !
b10001 (
b10001 )
1Q
b0 *
0R
0+
00
05
1:
0N
b10000 #
b10000 &
1"
#160000
1.
1-
b10010 !
b10010 (
b10010 )
0Q
b1 *
1R
1N
b10001 #
b10001 &
0"
#170000
03
02
0-
1.
0/
b10011 !
b10011 (
b10011 )
1Q
b0 *
0R
1+
0N
b10010 #
b10010 &
1"
#180000
13
12
0.
1/
1-
b10100 !
b10100 (
b10100 )
0Q
b11 *
1R
1N
b10011 #
b10011 &
0"
#190000
08
02
07
0-
0.
0/
13
04
b10101 !
b10101 (
b10101 )
1Q
b0 *
0R
0+
10
0N
b10100 #
b10100 &
1"
#200000
1.
1-
b10110 !
b10110 (
b10110 )
0Q
b1 *
1R
1N
b10101 #
b10101 &
0"
#210000
08
07
13
04
02
0-
1.
0/
b10111 !
b10111 (
b10111 )
1Q
b0 *
0R
1+
0N
b10110 #
b10110 &
1"
#220000
18
17
03
14
12
0.
1/
1-
b11000 !
b11000 (
b11000 )
0Q
b111 *
1R
1N
b10111 #
b10111 &
0"
#230000
0B
0A
1=
0>
02
07
0<
0-
0.
0/
03
04
18
09
b11001 !
b11001 (
b11001 )
1Q
b0 *
0R
0+
00
15
0N
b11000 #
b11000 &
1"
#240000
1.
1-
b11010 !
b11010 (
b11010 )
0Q
b1 *
1R
1N
b11001 #
b11001 &
0"
#250000
03
02
0-
1.
0/
b11011 !
b11011 (
b11011 )
1Q
b0 *
0R
1+
0N
b11010 #
b11010 &
1"
#260000
13
12
0.
1/
1-
b11100 !
b11100 (
b11100 )
0Q
b11 *
1R
1N
b11011 #
b11011 &
0"
#270000
0B
0A
1=
0>
0<
18
09
02
07
0-
0.
0/
13
04
b11101 !
b11101 (
b11101 )
1Q
b0 *
0R
0+
10
0N
b11100 #
b11100 &
1"
#280000
1.
1-
b11110 !
b11110 (
b11110 )
0Q
b1 *
1R
1N
b11101 #
b11101 &
0"
#290000
0B
0A
1=
0>
0<
18
09
07
13
04
02
0-
1.
0/
b11111 !
b11111 (
b11111 )
1Q
b0 *
0R
1+
0N
b11110 #
b11110 &
1"
#300000
1B
1A
0=
1>
1<
08
19
17
03
14
12
b100001 !
b100001 (
b100001 )
0.
b11110 *
1/
1,
0O
1N
b10 $
b10 '
b11111 #
b11111 &
0"
#310000
0G
02
07
0<
0A
0F
1.
0/
03
04
08
09
0=
0>
1B
b0 *
0C
b100010 !
b100010 (
b100010 )
0Q
0+
00
05
0:
1?
0N
b100000 #
b100000 &
1"
#320000
b100011 !
b100011 (
b100011 )
1Q
1N
b100001 #
b100001 &
0"
#330000
13
12
0.
b10 *
1/
b100100 !
b100100 (
b100100 )
0Q
1+
0N
b100010 #
b100010 &
1"
#340000
b100101 !
b100101 (
b100101 )
1Q
1N
b100011 #
b100011 &
0"
#350000
08
02
07
1.
0/
13
b0 *
04
b100110 !
b100110 (
b100110 )
0Q
0+
10
0N
b100100 #
b100100 &
1"
#360000
b100111 !
b100111 (
b100111 )
1Q
1N
b100101 #
b100101 &
0"
#370000
18
17
03
14
12
0.
b110 *
1/
b101000 !
b101000 (
b101000 )
0Q
1+
0N
b100110 #
b100110 &
1"
#380000
b101001 !
b101001 (
b101001 )
1Q
1N
b100111 #
b100111 &
0"
#390000
0=
02
07
0<
1.
0/
03
04
18
b0 *
09
b101010 !
b101010 (
b101010 )
0Q
0+
00
15
0N
b101000 #
b101000 &
1"
#400000
b101011 !
b101011 (
b101011 )
1Q
1N
b101001 #
b101001 &
0"
#410000
13
12
0.
b10 *
1/
b101100 !
b101100 (
b101100 )
0Q
1+
0N
b101010 #
b101010 &
1"
#420000
b101101 !
b101101 (
b101101 )
1Q
1N
b101011 #
b101011 &
0"
#430000
0=
0<
18
09
02
07
1.
0/
13
b0 *
04
b101110 !
b101110 (
b101110 )
0Q
0+
10
0N
b101100 #
b101100 &
1"
#440000
b101111 !
b101111 (
b101111 )
1Q
1N
b101101 #
b101101 &
0"
#450000
1=
1<
08
19
17
03
14
12
0.
b1110 *
1/
b110000 !
b110000 (
b110000 )
0Q
1+
0N
b101110 #
b101110 &
1"
#460000
b110010 !
b110010 (
b110010 )
1.
1-
b1111 *
1R
1O
1N
b11 $
b11 '
b101111 #
b101111 &
0"
#470000
0G
0F
02
1B
0C
0/
07
0<
0A
0-
1.
03
04
08
09
1=
0>
b110011 !
b110011 (
b110011 )
1Q
b0 *
0R
0+
00
05
1:
0N
b110000 #
b110000 &
1"
#480000
13
12
0.
1/
1-
b110100 !
b110100 (
b110100 )
0Q
b11 *
1R
1N
b110001 #
b110001 &
0"
#490000
0-
0.
b110101 !
b110101 (
b110101 )
1Q
b10 *
0R
1+
0N
b110010 #
b110010 &
1"
#500000
1.
1-
b110110 !
b110110 (
b110110 )
0Q
b11 *
1R
1N
b110011 #
b110011 &
0"
#510000
02
08
0/
07
0-
1.
13
04
b110111 !
b110111 (
b110111 )
1Q
b0 *
0R
0+
10
0N
b110100 #
b110100 &
1"
#520000
18
17
03
14
12
0.
1/
1-
b111000 !
b111000 (
b111000 )
0Q
b111 *
1R
1N
b110101 #
b110101 &
0"
#530000
0-
0.
b111001 !
b111001 (
b111001 )
1Q
b110 *
0R
1+
0N
b110110 #
b110110 &
1"
#540000
1.
1-
b111010 !
b111010 (
b111010 )
0Q
b111 *
1R
1N
b110111 #
b110111 &
0"
#550000
0G
0F
1B
0C
0A
02
1=
0>
0/
07
0<
0-
1.
03
04
18
09
b111011 !
b111011 (
b111011 )
1Q
b0 *
0R
0+
00
15
0N
b111000 #
b111000 &
1"
#560000
13
12
0.
1/
1-
b111100 !
b111100 (
b111100 )
0Q
b11 *
1R
1N
b111001 #
b111001 &
0"
#570000
0-
0.
b111101 !
b111101 (
b111101 )
1Q
b10 *
0R
1+
0N
b111010 #
b111010 &
1"
#580000
1.
1-
b111110 !
b111110 (
b111110 )
0Q
b11 *
1R
1N
b111011 #
b111011 &
0"
#590000
0G
0F
1B
0C
0A
1=
0>
0<
02
18
09
0/
07
0-
1.
13
04
b111111 !
b111111 (
b111111 )
1Q
b0 *
0R
0+
10
0N
b111100 #
b111100 &
1"
#600000
1G
1F
0B
1C
1A
0=
1>
1<
08
19
17
03
14
12
0.
1/
1-
b1000000 !
b1000000 (
b1000000 )
0Q
b111111 *
1R
1N
b111101 #
b111101 &
0"
#610000
0-
0.
b1000001 !
b1000001 (
b1000001 )
1Q
b111110 *
0R
1+
0N
b111110 #
b111110 &
1"
#620000
02
1.
b111100 *
0/
b1000011 !
b1000011 (
b1000011 )
03
0,
11
0O
1N
b100 $
b100 '
b111111 #
b111111 &
0"
#630000
0L
07
0<
0A
0F
0K
0.
13
04
08
09
0=
0>
0B
0C
1G
b0 *
0H
b1000100 !
b1000100 (
b1000100 )
0Q
0+
00
05
0:
0?
1D
0N
b1000000 #
b1000000 &
1"
#640000
b1000101 !
b1000101 (
b1000101 )
1Q
1N
b1000001 #
b1000001 &
0"
#650000
1.
b1000110 !
b1000110 (
b1000110 )
0Q
1+
0N
b1000010 #
b1000010 &
1"
#660000
b1000111 !
b1000111 (
b1000111 )
1Q
1N
b1000011 #
b1000011 &
0"
#670000
18
17
0.
03
b100 *
14
b1001000 !
b1001000 (
b1001000 )
0Q
0+
10
0N
b1000100 #
b1000100 &
1"
#680000
b1001001 !
b1001001 (
b1001001 )
1Q
1N
b1000101 #
b1000101 &
0"
#690000
1.
b1001010 !
b1001010 (
b1001010 )
0Q
1+
0N
b1000110 #
b1000110 &
1"
#700000
b1001011 !
b1001011 (
b1001011 )
1Q
1N
b1000111 #
b1000111 &
0"
#710000
0=
07
0<
0.
13
04
18
b0 *
09
b1001100 !
b1001100 (
b1001100 )
0Q
0+
00
15
0N
b1001000 #
b1001000 &
1"
#720000
b1001101 !
b1001101 (
b1001101 )
1Q
1N
b1001001 #
b1001001 &
0"
#730000
1.
b1001110 !
b1001110 (
b1001110 )
0Q
1+
0N
b1001010 #
b1001010 &
1"
#740000
b1001111 !
b1001111 (
b1001111 )
1Q
1N
b1001011 #
b1001011 &
0"
#750000
1=
1<
08
19
17
0.
03
b1100 *
14
b1010000 !
b1010000 (
b1010000 )
0Q
0+
10
0N
b1001100 #
b1001100 &
1"
#760000
b1010001 !
b1010001 (
b1010001 )
1Q
1N
b1001101 #
b1001101 &
0"
#770000
1.
b1010010 !
b1010010 (
b1010010 )
0Q
1+
0N
b1001110 #
b1001110 &
1"
#780000
13
12
b1010100 !
b1010100 (
b1010100 )
0.
1/
1-
b1111 *
1R
1O
1N
b101 $
b101 '
b1001111 #
b1001111 &
0"
#790000
07
04
0B
02
0<
0A
0-
0.
0/
13
08
09
1=
0>
b1010101 !
b1010101 (
b1010101 )
1Q
b0 *
0R
0+
00
05
1:
0N
b1010000 #
b1010000 &
1"
#800000
1.
1-
b1010110 !
b1010110 (
b1010110 )
0Q
b1 *
1R
1N
b1010001 #
b1010001 &
0"
#810000
08
07
13
04
02
0-
1.
0/
b1010111 !
b1010111 (
b1010111 )
1Q
b0 *
0R
1+
0N
b1010010 #
b1010010 &
1"
#820000
18
17
03
14
12
0.
1/
1-
b1011000 !
b1011000 (
b1011000 )
0Q
b111 *
1R
1N
b1010011 #
b1010011 &
0"
#830000
02
0-
0.
0/
03
b1011001 !
b1011001 (
b1011001 )
1Q
b100 *
0R
0+
10
0N
b1010100 #
b1010100 &
1"
#840000
1.
1-
b1011010 !
b1011010 (
b1011010 )
0Q
b101 *
1R
1N
b1010101 #
b1010101 &
0"
#850000
03
02
0-
1.
0/
b1011011 !
b1011011 (
b1011011 )
1Q
b100 *
0R
1+
0N
b1010110 #
b1010110 &
1"
#860000
13
12
0.
1/
1-
b1011100 !
b1011100 (
b1011100 )
0Q
b111 *
1R
1N
b1010111 #
b1010111 &
0"
#870000
0B
07
0A
04
1=
0>
02
0<
0-
0.
0/
13
18
09
b1011101 !
b1011101 (
b1011101 )
1Q
b0 *
0R
0+
00
15
0N
b1011000 #
b1011000 &
1"
#880000
1.
1-
b1011110 !
b1011110 (
b1011110 )
0Q
b1 *
1R
1N
b1011001 #
b1011001 &
0"
#890000
0B
0A
1=
0>
0<
18
09
07
13
04
02
0-
1.
0/
b1011111 !
b1011111 (
b1011111 )
1Q
b0 *
0R
1+
0N
b1011010 #
b1011010 &
1"
#900000
1B
1A
0=
1>
1<
08
19
17
03
14
12
0.
1/
1-
b1100000 !
b1100000 (
b1100000 )
0Q
b11111 *
1R
1N
b1011011 #
b1011011 &
0"
#910000
02
0-
0.
0/
03
b1100001 !
b1100001 (
b1100001 )
1Q
b11100 *
0R
0+
10
0N
b1011100 #
b1011100 &
1"
#920000
1.
1-
b1100010 !
b1100010 (
b1100010 )
0Q
b11101 *
1R
1N
b1011101 #
b1011101 &
0"
#930000
03
02
0-
1.
0/
b1100011 !
b1100011 (
b1100011 )
1Q
b11100 *
0R
1+
0N
b1011110 #
b1011110 &
1"
#940000
13
12
b1100101 !
b1100101 (
b1100101 )
0.
b11110 *
1/
1,
0O
1N
b110 $
b110 '
b1011111 #
b1011111 &
0"
#950000
0L
07
0K
04
1G
0H
02
0<
0A
0F
1.
0/
13
08
09
0=
0>
1B
b0 *
0C
b1100110 !
b1100110 (
b1100110 )
0Q
0+
00
05
0:
1?
0N
b1100000 #
b1100000 &
1"
#960000
b1100111 !
b1100111 (
b1100111 )
1Q
1N
b1100001 #
b1100001 &
0"
#970000
18
17
03
14
12
0.
b110 *
1/
b1101000 !
b1101000 (
b1101000 )
0Q
1+
0N
b1100010 #
b1100010 &
1"
#980000
b1101001 !
b1101001 (
b1101001 )
1Q
1N
b1100011 #
b1100011 &
0"
#990000
02
1.
b100 *
0/
03
b1101010 !
b1101010 (
b1101010 )
0Q
0+
10
0N
b1100100 #
b1100100 &
1"
#1000000
b1101011 !
b1101011 (
b1101011 )
1Q
1N
b1100101 #
b1100101 &
0"
#1010000
13
12
0.
b110 *
1/
b1101100 !
b1101100 (
b1101100 )
0Q
1+
0N
b1100110 #
b1100110 &
1"
#1020000
b1101101 !
b1101101 (
b1101101 )
1Q
1N
b1100111 #
b1100111 &
0"
#1030000
07
04
0=
02
0<
1.
0/
13
18
b0 *
09
b1101110 !
b1101110 (
b1101110 )
0Q
0+
00
15
0N
b1101000 #
b1101000 &
1"
#1040000
b1101111 !
b1101111 (
b1101111 )
1Q
1N
b1101001 #
b1101001 &
0"
#1050000
1=
1<
08
19
17
03
14
12
0.
b1110 *
1/
b1110000 !
b1110000 (
b1110000 )
0Q
1+
0N
b1101010 #
b1101010 &
1"
#1060000
b1110001 !
b1110001 (
b1110001 )
1Q
1N
b1101011 #
b1101011 &
0"
#1070000
02
1.
b1100 *
0/
03
b1110010 !
b1110010 (
b1110010 )
0Q
0+
10
0N
b1101100 #
b1101100 &
1"
#1080000
b1110011 !
b1110011 (
b1110011 )
1Q
1N
b1101101 #
b1101101 &
0"
#1090000
13
12
0.
b1110 *
1/
b1110100 !
b1110100 (
b1110100 )
0Q
1+
0N
b1101110 #
b1101110 &
1"
#1100000
b1110110 !
b1110110 (
b1110110 )
1.
1-
b1111 *
1R
1O
1N
b111 $
b111 '
b1101111 #
b1101111 &
0"
#1110000
0L
0K
07
1G
0H
04
0F
02
1B
0C
0/
0<
0A
0-
1.
13
08
09
1=
0>
b1110111 !
b1110111 (
b1110111 )
1Q
b0 *
0R
0+
00
05
1:
0N
b1110000 #
b1110000 &
1"
#1120000
18
17
03
14
12
0.
1/
1-
b1111000 !
b1111000 (
b1111000 )
0Q
b111 *
1R
1N
b1110001 #
b1110001 &
0"
#1130000
0-
0.
b1111001 !
b1111001 (
b1111001 )
1Q
b110 *
0R
1+
0N
b1110010 #
b1110010 &
1"
#1140000
1.
1-
b1111010 !
b1111010 (
b1111010 )
0Q
b111 *
1R
1N
b1110011 #
b1110011 &
0"
#1150000
02
0/
0-
1.
03
b1111011 !
b1111011 (
b1111011 )
1Q
b100 *
0R
0+
10
0N
b1110100 #
b1110100 &
1"
#1160000
13
12
0.
1/
1-
b1111100 !
b1111100 (
b1111100 )
0Q
b111 *
1R
1N
b1110101 #
b1110101 &
0"
#1170000
0-
0.
b1111101 !
b1111101 (
b1111101 )
1Q
b110 *
0R
1+
0N
b1110110 #
b1110110 &
1"
#1180000
1.
1-
b1111110 !
b1111110 (
b1111110 )
0Q
b111 *
1R
1N
b1110111 #
b1110111 &
0"
#1190000
0L
0K
1G
0H
0F
07
1B
0C
04
0A
02
1=
0>
0/
0<
0-
1.
13
18
09
b1111111 !
b1111111 (
b1111111 )
1Q
b0 *
0R
0+
00
15
0N
b1111000 #
b1111000 &
1"
#1200000
1L
1K
0G
1H
1F
0B
1C
1A
0=
1>
1<
08
19
17
03
14
12
0.
1/
1-
b10000000 !
b10000000 (
b10000000 )
0Q
b1111111 *
1R
1N
b1111001 #
b1111001 &
0"
#1210000
0-
0.
b10000001 !
b10000001 (
b10000001 )
1Q
b1111110 *
0R
1+
0N
b1111010 #
b1111010 &
1"
#1220000
1.
1-
b10000010 !
b10000010 (
b10000010 )
0Q
b1111111 *
1R
1N
b1111011 #
b1111011 &
0"
#1230000
02
0/
0-
1.
03
b10000011 !
b10000011 (
b10000011 )
1Q
b1111100 *
0R
0+
10
0N
b1111100 #
b1111100 &
1"
#1240000
13
12
0.
1/
1-
b10000100 !
b10000100 (
b10000100 )
0Q
b1111111 *
1R
1N
b1111101 #
b1111101 &
0"
#1250000
0-
0.
b10000101 !
b10000101 (
b10000101 )
1Q
b1111110 *
0R
1+
0N
b1111110 #
b1111110 &
1"
#1260000
07
04
02
1.
b1111000 *
0/
13
b10000111 !
b10000111 (
b10000111 )
08
0,
01
16
0O
1N
b1000 $
b1000 '
b1111111 #
b1111111 &
0"
#1270000
0<
0A
0F
0K
0.
03
18
09
0=
0>
0B
0C
0G
0H
1L
b0 *
0M
b10001000 !
b10001000 (
b10001000 )
0Q
0+
00
05
0:
0?
0D
1I
0N
b10000000 #
b10000000 &
1"
#1280000
b10001001 !
b10001001 (
b10001001 )
1Q
1N
b10000001 #
b10000001 &
0"
#1290000
1.
b10001010 !
b10001010 (
b10001010 )
0Q
1+
0N
b10000010 #
b10000010 &
1"
#1300000
b10001011 !
b10001011 (
b10001011 )
1Q
1N
b10000011 #
b10000011 &
0"
#1310000
0.
13
b10001100 !
b10001100 (
b10001100 )
0Q
0+
10
0N
b10000100 #
b10000100 &
1"
#1320000
b10001101 !
b10001101 (
b10001101 )
1Q
1N
b10000101 #
b10000101 &
0"
#1330000
1.
b10001110 !
b10001110 (
b10001110 )
0Q
1+
0N
b10000110 #
b10000110 &
1"
#1340000
b10001111 !
b10001111 (
b10001111 )
1Q
1N
b10000111 #
b10000111 &
0"
#1350000
1=
1<
0.
03
08
b1000 *
19
b10010000 !
b10010000 (
b10010000 )
0Q
0+
00
15
0N
b10001000 #
b10001000 &
1"
#1360000
b10010001 !
b10010001 (
b10010001 )
1Q
1N
b10001001 #
b10001001 &
0"
#1370000
1.
b10010010 !
b10010010 (
b10010010 )
0Q
1+
0N
b10001010 #
b10001010 &
1"
#1380000
b10010011 !
b10010011 (
b10010011 )
1Q
1N
b10001011 #
b10001011 &
0"
#1390000
0.
13
b10010100 !
b10010100 (
b10010100 )
0Q
0+
10
0N
b10001100 #
b10001100 &
1"
#1400000
b10010101 !
b10010101 (
b10010101 )
1Q
1N
b10001101 #
b10001101 &
0"
#1410000
1.
b10010110 !
b10010110 (
b10010110 )
0Q
1+
0N
b10001110 #
b10001110 &
1"
#1420000
18
17
03
14
12
b10011000 !
b10011000 (
b10011000 )
0.
1/
1-
b1111 *
1R
1O
1N
b1001 $
b1001 '
b10001111 #
b10001111 &
0"
#1430000
0<
09
0B
02
07
0A
0-
0.
0/
03
04
18
1=
0>
b10011001 !
b10011001 (
b10011001 )
1Q
b0 *
0R
0+
00
05
1:
0N
b10010000 #
b10010000 &
1"
#1440000
1.
1-
b10011010 !
b10011010 (
b10011010 )
0Q
b1 *
1R
1N
b10010001 #
b10010001 &
0"
#1450000
03
02
0-
1.
0/
b10011011 !
b10011011 (
b10011011 )
1Q
b0 *
0R
1+
0N
b10010010 #
b10010010 &
1"
#1460000
13
12
0.
1/
1-
b10011100 !
b10011100 (
b10011100 )
0Q
b11 *
1R
1N
b10010011 #
b10010011 &
0"
#1470000
0B
0A
1=
0>
0<
18
09
02
07
0-
0.
0/
13
04
b10011101 !
b10011101 (
b10011101 )
1Q
b0 *
0R
0+
10
0N
b10010100 #
b10010100 &
1"
#1480000
1.
1-
b10011110 !
b10011110 (
b10011110 )
0Q
b1 *
1R
1N
b10010101 #
b10010101 &
0"
#1490000
0B
0A
1=
0>
0<
18
09
07
13
04
02
0-
1.
0/
b10011111 !
b10011111 (
b10011111 )
1Q
b0 *
0R
1+
0N
b10010110 #
b10010110 &
1"
#1500000
1B
1A
0=
1>
1<
08
19
17
03
14
12
0.
1/
1-
b10100000 !
b10100000 (
b10100000 )
0Q
b11111 *
1R
1N
b10010111 #
b10010111 &
0"
#1510000
02
07
0-
0.
0/
03
04
08
b10100001 !
b10100001 (
b10100001 )
1Q
b11000 *
0R
0+
00
15
0N
b10011000 #
b10011000 &
1"
#1520000
1.
1-
b10100010 !
b10100010 (
b10100010 )
0Q
b11001 *
1R
1N
b10011001 #
b10011001 &
0"
#1530000
03
02
0-
1.
0/
b10100011 !
b10100011 (
b10100011 )
1Q
b11000 *
0R
1+
0N
b10011010 #
b10011010 &
1"
#1540000
13
12
0.
1/
1-
b10100100 !
b10100100 (
b10100100 )
0Q
b11011 *
1R
1N
b10011011 #
b10011011 &
0"
#1550000
08
02
07
0-
0.
0/
13
04
b10100101 !
b10100101 (
b10100101 )
1Q
b11000 *
0R
0+
10
0N
b10011100 #
b10011100 &
1"
#1560000
1.
1-
b10100110 !
b10100110 (
b10100110 )
0Q
b11001 *
1R
1N
b10011101 #
b10011101 &
0"
#1570000
08
07
13
04
02
0-
1.
0/
b10100111 !
b10100111 (
b10100111 )
1Q
b11000 *
0R
1+
0N
b10011110 #
b10011110 &
1"
#1580000
18
17
03
14
12
b10101001 !
b10101001 (
b10101001 )
0.
b11110 *
1/
1,
0O
1N
b1010 $
b1010 '
b10011111 #
b10011111 &
0"
#1590000
0<
09
0G
02
07
0A
0F
1.
0/
03
04
18
0=
0>
1B
b0 *
0C
b10101010 !
b10101010 (
b10101010 )
0Q
0+
00
05
0:
1?
0N
b10100000 #
b10100000 &
1"
#1600000
b10101011 !
b10101011 (
b10101011 )
1Q
1N
b10100001 #
b10100001 &
0"
#1610000
13
12
0.
b10 *
1/
b10101100 !
b10101100 (
b10101100 )
0Q
1+
0N
b10100010 #
b10100010 &
1"
#1620000
b10101101 !
b10101101 (
b10101101 )
1Q
1N
b10100011 #
b10100011 &
0"
#1630000
0=
0<
18
09
02
07
1.
0/
13
b0 *
04
b10101110 !
b10101110 (
b10101110 )
0Q
0+
10
0N
b10100100 #
b10100100 &
1"
#1640000
b10101111 !
b10101111 (
b10101111 )
1Q
1N
b10100101 #
b10100101 &
0"
#1650000
1=
1<
08
19
17
03
14
12
0.
b1110 *
1/
b10110000 !
b10110000 (
b10110000 )
0Q
1+
0N
b10100110 #
b10100110 &
1"
#1660000
b10110001 !
b10110001 (
b10110001 )
1Q
1N
b10100111 #
b10100111 &
0"
#1670000
02
07
1.
0/
03
b1000 *
04
08
b10110010 !
b10110010 (
b10110010 )
0Q
0+
00
15
0N
b10101000 #
b10101000 &
1"
#1680000
b10110011 !
b10110011 (
b10110011 )
1Q
1N
b10101001 #
b10101001 &
0"
#1690000
13
12
0.
b1010 *
1/
b10110100 !
b10110100 (
b10110100 )
0Q
1+
0N
b10101010 #
b10101010 &
1"
#1700000
b10110101 !
b10110101 (
b10110101 )
1Q
1N
b10101011 #
b10101011 &
0"
#1710000
08
02
07
1.
0/
13
b1000 *
04
b10110110 !
b10110110 (
b10110110 )
0Q
0+
10
0N
b10101100 #
b10101100 &
1"
#1720000
b10110111 !
b10110111 (
b10110111 )
1Q
1N
b10101101 #
b10101101 &
0"
#1730000
18
17
03
14
12
0.
b1110 *
1/
b10111000 !
b10111000 (
b10111000 )
0Q
1+
0N
b10101110 #
b10101110 &
1"
#1740000
b10111010 !
b10111010 (
b10111010 )
1.
1-
b1111 *
1R
1O
1N
b1011 $
b1011 '
b10101111 #
b10101111 &
0"
#1750000
0G
0<
0F
02
09
1B
0C
0/
07
0A
0-
1.
03
04
18
1=
0>
b10111011 !
b10111011 (
b10111011 )
1Q
b0 *
0R
0+
00
05
1:
0N
b10110000 #
b10110000 &
1"
#1760000
13
12
0.
1/
1-
b10111100 !
b10111100 (
b10111100 )
0Q
b11 *
1R
1N
b10110001 #
b10110001 &
0"
#1770000
0-
0.
b10111101 !
b10111101 (
b10111101 )
1Q
b10 *
0R
1+
0N
b10110010 #
b10110010 &
1"
#1780000
1.
1-
b10111110 !
b10111110 (
b10111110 )
0Q
b11 *
1R
1N
b10110011 #
b10110011 &
0"
#1790000
0G
0F
1B
0C
0A
1=
0>
0<
02
18
09
0/
07
0-
1.
13
04
b10111111 !
b10111111 (
b10111111 )
1Q
b0 *
0R
0+
10
0N
b10110100 #
b10110100 &
1"
#1800000
1G
1F
0B
1C
1A
0=
1>
1<
08
19
17
03
14
12
0.
1/
1-
b11000000 !
b11000000 (
b11000000 )
0Q
b111111 *
1R
1N
b10110101 #
b10110101 &
0"
#1810000
0-
0.
b11000001 !
b11000001 (
b11000001 )
1Q
b111110 *
0R
1+
0N
b10110110 #
b10110110 &
1"
#1820000
1.
1-
b11000010 !
b11000010 (
b11000010 )
0Q
b111111 *
1R
1N
b10110111 #
b10110111 &
0"
#1830000
02
0/
07
0-
1.
03
04
08
b11000011 !
b11000011 (
b11000011 )
1Q
b111000 *
0R
0+
00
15
0N
b10111000 #
b10111000 &
1"
#1840000
13
12
0.
1/
1-
b11000100 !
b11000100 (
b11000100 )
0Q
b111011 *
1R
1N
b10111001 #
b10111001 &
0"
#1850000
0-
0.
b11000101 !
b11000101 (
b11000101 )
1Q
b111010 *
0R
1+
0N
b10111010 #
b10111010 &
1"
