case_and_its_Associated_Caveats/incomp_case.v
module incomp_case (
	input 			i0 , 
	input 			i1 , 
	input 			i2 , 
	input 		[1:0] 	sel, 
	output 	reg 		y
);

always @ (*)
begin
	case(sel)
		2'b00 : y = i0;
		2'b01 : y = i1;
	endcase
end

endmodule

case_and_its_Associated_Caveats/tb_incomp_case.v
`timescale 1ns / 1ps
module tb_incomp_case;
	//input
	reg i0,i1,i2;
	reg [1:0] sel;
	// Output
	wire y;
	//TB_SIGNALS
        reg clk,reset;	

        // Instantiate the Unit Under Test (UUT)
	incomp_case uut (
		.sel(sel),
		.i0(i0),
		.i1(i1),
		.i2(i2),
		.y(y)
	);

	initial begin
	$dumpfile("tb_incomp_case.vcd");
	$dumpvars(0,tb_incomp_case);
	// Initialize Inputs
	i0 = 1'b0;
	i1 = 1'b0;
	i2 = 1'b0;
	clk = 1'b0;
	reset = 1'b0; #1;
	reset = 1'b1; #10;
	reset = 1'b0; 

	
	#5000 $finish;
	end

	always #317 i0 = ~i0;
	always #600 clk = ~clk;
	always #37 i1 = ~i1;
	always #57 i2 = ~i2;


	always @(posedge clk , posedge reset)
	begin
	if(reset)
		sel <= 2'b00;
	else
		sel <= sel + 1;
	end

endmodule

case_and_its_Associated_Caveats/tb_incomp_case.vcd
$date
	Sat Jun  5 12:22:26 2021
$end
$version
	Icarus Verilog
$end
$timescale
	1ps
$end
$scope module tb_incomp_case $end
$var wire 1 ! y $end
$var reg 1 " clk $end
$var reg 1 # i0 $end
$var reg 1 $ i1 $end
$var reg 1 % i2 $end
$var reg 1 & reset $end
$var reg 2 ' sel [1:0] $end
$scope module uut $end
$var wire 1 # i0 $end
$var wire 1 $ i1 $end
$var wire 1 % i2 $end
$var wire 2 ( sel [1:0] $end
$var reg 1 ! y $end
$upscope $end
$upscope $end
$enddefinitions $end
#0
$dumpvars
bx (
bx '
0&
0%
0$
0#
0"
x!
$end
#1000
0!
b0 '
b0 (
1&
#11000
0&
#37000
1$
#57000
1%
#74000
0$
#111000
1$
#114000
0%
#148000
0$
#171000
1%
#185000
1$
#222000
0$
#228000
0%
#259000
1$
#285000
1%
#296000
0$
#317000
1!
1#
#333000
1$
#342000
0%
#370000
0$
#399000
1%
#407000
1$
#444000
0$
#456000
0%
#481000
1$
#513000
1%
#518000
0$
#555000
1$
#570000
0%
#592000
0$
#600000
0!
b1 '
b1 (
1"
#627000
1%
#629000
1!
1$
#634000
0#
#666000
0!
0$
#684000
0%
#703000
1!
1$
#740000
0!
0$
#741000
1%
#777000
1!
1$
#798000
0%
#814000
0!
0$
#851000
1!
1$
#855000
1%
#888000
0!
0$
#912000
0%
#925000
1!
1$
#951000
1#
#962000
0!
0$
#969000
1%
#999000
1!
1$
#1026000
0%
#1036000
0!
0$
#1073000
1!
1$
#1083000
1%
#1110000
0!
0$
#1140000
0%
#1147000
1!
1$
#1184000
0!
0$
#1197000
1%
#1200000
0"
#1221000
1!
1$
#1254000
0%
#1258000
0!
0$
#1268000
0#
#1295000
1!
1$
#1311000
1%
#1332000
0!
0$
#1368000
0%
#1369000
1!
1$
#1406000
0!
0$
#1425000
1%
#1443000
1!
1$
#1480000
0!
0$
#1482000
0%
#1517000
1!
1$
#1539000
1%
#1554000
0!
0$
#1585000
1#
#1591000
1!
1$
#1596000
0%
#1628000
0!
0$
#1653000
1%
#1665000
1!
1$
#1702000
0!
0$
#1710000
0%
#1739000
1!
1$
#1767000
1%
#1776000
0!
0$
#1800000
b10 '
b10 (
1"
#1813000
1$
#1824000
0%
#1850000
0$
#1881000
1%
#1887000
1$
#1902000
0#
#1924000
0$
#1938000
0%
#1961000
1$
#1995000
1%
#1998000
0$
#2035000
1$
#2052000
0%
#2072000
0$
#2109000
1$
1%
#2146000
0$
#2166000
0%
#2183000
1$
#2219000
1#
#2220000
0$
#2223000
1%
#2257000
1$
#2280000
0%
#2294000
0$
#2331000
1$
#2337000
1%
#2368000
0$
#2394000
0%
#2400000
0"
#2405000
1$
#2442000
0$
#2451000
1%
#2479000
1$
#2508000
0%
#2516000
0$
#2536000
0#
#2553000
1$
#2565000
1%
#2590000
0$
#2622000
0%
#2627000
1$
#2664000
0$
#2679000
1%
#2701000
1$
#2736000
0%
#2738000
0$
#2775000
1$
#2793000
1%
#2812000
0$
#2849000
1$
#2850000
0%
#2853000
1#
#2886000
0$
#2907000
1%
#2923000
1$
#2960000
0$
#2964000
0%
#2997000
1$
#3000000
b11 '
b11 (
1"
#3021000
1%
#3034000
0$
#3071000
1$
#3078000
0%
#3108000
0$
#3135000
1%
#3145000
1$
#3170000
0#
#3182000
0$
#3192000
0%
#3219000
1$
#3249000
1%
#3256000
0$
#3293000
1$
#3306000
0%
#3330000
0$
#3363000
1%
#3367000
1$
#3404000
0$
#3420000
0%
#3441000
1$
#3477000
1%
#3478000
0$
#3487000
1#
#3515000
1$
#3534000
0%
#3552000
0$
#3589000
1$
#3591000
1%
#3600000
0"
#3626000
0$
#3648000
0%
#3663000
1$
#3700000
0$
#3705000
1%
#3737000
1$
#3762000
0%
#3774000
0$
#3804000
0#
#3811000
1$
#3819000
1%
#3848000
0$
#3876000
0%
#3885000
1$
#3922000
0$
#3933000
1%
#3959000
1$
#3990000
0%
#3996000
0$
#4033000
1$
#4047000
1%
#4070000
0$
#4104000
0%
#4107000
1$
#4121000
1#
#4144000
0$
#4161000
1%
#4181000
1$
#4200000
1!
b0 '
b0 (
1"
#4218000
0$
0%
#4255000
1$
#4275000
1%
#4292000
0$
#4329000
1$
#4332000
0%
#4366000
0$
#4389000
1%
#4403000
1$
#4438000
0!
0#
#4440000
0$
#4446000
0%
#4477000
1$
#4503000
1%
#4514000
0$
#4551000
1$
#4560000
0%
#4588000
0$
#4617000
1%
#4625000
1$
#4662000
0$
#4674000
0%
#4699000
1$
#4731000
1%
#4736000
0$
#4755000
1!
1#
#4773000
1$
#4788000
0%
#4800000
0"
#4810000
0$
#4845000
1%
#4847000
1$
#4884000
0$
#4902000
0%
#4921000
1$
#4958000
0$
#4959000
1%
#4995000
1$
